
{
 " Name ": "Save 1",
 "FileSource": "C:/Users/Hanton/Desktop/Tout/CESI/ASSOS\log.json",
 "FileTarget": "C:/Users/Hanton/Desktop/Tout/CESI/A1\log.json",
 "destPath": '' ,
 "FileSize": 875672,
 "FileTransferTime": 0.0042,
 "time": "15/12/2021 13:49:06",
 "Encryption time": 0.005,
},
{
 " Name ": "Save 1",
 "FileSource": "C:/Users/Hanton/Desktop/Tout/CESI/ASSOS\logIRT.json",
 "FileTarget": "C:/Users/Hanton/Desktop/Tout/CESI/A1\logIRT.json",
 "destPath": '' ,
 "FileSize": 150,
 "FileTransferTime": 0.0041,
 "time": "15/12/2021 13:49:06",
 "Encryption time": 0.0047,
},
{
 " Name ": "Save 1",
 "FileSource": "C:/Users/Hanton/Desktop/Tout/CESI/ASSOS\message.txt",
 "FileTarget": "C:/Users/Hanton/Desktop/Tout/CESI/A1\message.txt",
 "destPath": '' ,
 "FileSize": 1276232,
 "FileTransferTime": 0.0081,
 "time": "15/12/2021 13:49:06",
 "Encryption time": 0,
},
{
 " Name ": "Save 1",
 "FileSource": "C:/Users/Hanton/Desktop/Tout/CESI/ASSOS\Papier banque.pdf",
 "FileTarget": "C:/Users/Hanton/Desktop/Tout/CESI/A1\Papier banque.pdf",
 "destPath": '' ,
 "FileSize": 478403,
 "FileTransferTime": 0.0052,
 "time": "15/12/2021 13:49:06",
 "Encryption time": 0,
},
{
 " Name ": "Save 1",
 "FileSource": "C:/Users/Hanton/Desktop/Tout/CESI/ASSOS\Papier_banque_vf.pdf",
 "FileTarget": "C:/Users/Hanton/Desktop/Tout/CESI/A1\Papier_banque_vf.pdf",
 "destPath": '' ,
 "FileSize": 789728,
 "FileTransferTime": 0.0057,
 "time": "15/12/2021 13:49:06",
 "Encryption time": 0,
},
{
 " Name ": "Save 1",
 "FileSource": "C:/Users/Hanton/Desktop/Tout/CESI/ASSOS\test.json",
 "FileTarget": "C:/Users/Hanton/Desktop/Tout/CESI/A1\test.json",
 "destPath": '' ,
 "FileSize": 153,
 "FileTransferTime": 0.0053,
 "time": "15/12/2021 13:49:06",
 "Encryption time": 0.0053,
},
{
 " Name ": "Save 1",
 "FileSource": "C:/Users/Hanton/Desktop/Tout/CESI/ASSOS\Cresi Racing\Texte.docx",
 "FileTarget": "C:/Users/Hanton/Desktop/Tout/CESI/A1\Cresi Racing\Texte.docx",
 "destPath": '' ,
 "FileSize": 29397,
 "FileTransferTime": 0.0057,
 "time": "15/12/2021 13:49:06",
 "Encryption time": 0,
},
{
 " Name ": "Save 1",
 "FileSource": "C:/Users/Hanton/Desktop/Tout/CESI/ASSOS\JDR\fiche perso Ganir TES.docx",
 "FileTarget": "C:/Users/Hanton/Desktop/Tout/CESI/A1\JDR\fiche perso Ganir TES.docx",
 "destPath": '' ,
 "FileSize": 1876866,
 "FileTransferTime": 0.0046,
 "time": "15/12/2021 13:49:06",
 "Encryption time": 0,
},
{
 " Name ": "Save 1",
 "FileSource": "C:/Users/Hanton/Desktop/Tout/CESI/ASSOS\Sport\message.txt",
 "FileTarget": "C:/Users/Hanton/Desktop/Tout/CESI/A1\Sport\message.txt",
 "destPath": '' ,
 "FileSize": 1276232,
 "FileTransferTime": 0.0056,
 "time": "15/12/2021 13:49:07",
 "Encryption time": 0,
},
{
 " Name ": "Save 1",
 "FileSource": "C:/Users/Hanton/Desktop/Tout/CESI/ASSOS\Sport\Projet CESI SPORT.docx",
 "FileTarget": "C:/Users/Hanton/Desktop/Tout/CESI/A1\Sport\Projet CESI SPORT.docx",
 "destPath": '' ,
 "FileSize": 2293225,
 "FileTransferTime": 0.0048,
 "time": "15/12/2021 13:49:07",
 "Encryption time": 0,
},
{
 " Name ": "Save 1",
 "FileSource": "C:/Users/Hanton/Desktop/Tout/CESI/ASSOS\Wild box\message.txt",
 "FileTarget": "C:/Users/Hanton/Desktop/Tout/CESI/A1\Wild box\message.txt",
 "destPath": '' ,
 "FileSize": 1276232,
 "FileTransferTime": 0.0063,
 "time": "15/12/2021 13:49:07",
 "Encryption time": 0,
},
{
 " Name ": "Save 1",
 "FileSource": "C:/Users/Hanton/Desktop/Tout/CESI/ASSOS\Wild box\CROPS Saver\carotte4.png",
 "FileTarget": "C:/Users/Hanton/Desktop/Tout/CESI/A1\Wild box\CROPS Saver\carotte4.png",
 "destPath": '' ,
 "FileSize": 1618473,
 "FileTransferTime": 0.0055,
 "time": "15/12/2021 13:49:07",
 "Encryption time": 0,
},
{
 " Name ": "Save 1",
 "FileSource": "C:/Users/Hanton/Desktop/Tout/CESI/ASSOS\Wild box\CROPS Saver\Projectile.png",
 "FileTarget": "C:/Users/Hanton/Desktop/Tout/CESI/A1\Wild box\CROPS Saver\Projectile.png",
 "destPath": '' ,
 "FileSize": 372,
 "FileTransferTime": 0.0077,
 "time": "15/12/2021 13:49:07",
 "Encryption time": 0,
},
{
 " Name ": "Save 1",
 "FileSource": "C:/Users/Hanton/Desktop/Tout/CESI/ASSOS\Wild box\Projet solo\Stratégie tour par tour en 1v1.docx",
 "FileTarget": "C:/Users/Hanton/Desktop/Tout/CESI/A1\Wild box\Projet solo\Stratégie tour par tour en 1v1.docx",
 "destPath": '' ,
 "FileSize": 25719,
 "FileTransferTime": 0.1856,
 "time": "15/12/2021 13:49:08",
 "Encryption time": 0,
},
{
 " Name ": "Save 1",
 "FileSource": "C:/Users/Hanton/Desktop/Tout/CESI/ASSOS\Wild box\Projet solo\test map.tmx",
 "FileTarget": "C:/Users/Hanton/Desktop/Tout/CESI/A1\Wild box\Projet solo\test map.tmx",
 "destPath": '' ,
 "FileSize": 20552,
 "FileTransferTime": 0.0057,
 "time": "15/12/2021 13:49:08",
 "Encryption time": 0,
},
{
 " Name ": "Save 1",
 "FileSource": "C:/Users/Hanton/Desktop/Tout/CESI/ASSOS\Wild box\Images\Hanton\Hanton black box.png",
 "FileTarget": "C:/Users/Hanton/Desktop/Tout/CESI/A1\Wild box\Images\Hanton\Hanton black box.png",
 "destPath": '' ,
 "FileSize": 18654,
 "FileTransferTime": 0.0076,
 "time": "15/12/2021 13:49:08",
 "Encryption time": 0,
},
{
 " Name ": "Save 1",
 "FileSource": "C:/Users/Hanton/Desktop/Tout/CESI/ASSOS\Wild box\Images\Hanton\Hanton Pixel Perfect.png",
 "FileTarget": "C:/Users/Hanton/Desktop/Tout/CESI/A1\Wild box\Images\Hanton\Hanton Pixel Perfect.png",
 "destPath": '' ,
 "FileSize": 528,
 "FileTransferTime": 0.005,
 "time": "15/12/2021 13:49:08",
 "Encryption time": 0,
},
{
 " Name ": "Save 1",
 "FileSource": "C:/Users/Hanton/Desktop/Tout/CESI/ASSOS\Wild box\Images\Hanton\Hanton white box.png",
 "FileTarget": "C:/Users/Hanton/Desktop/Tout/CESI/A1\Wild box\Images\Hanton\Hanton white box.png",
 "destPath": '' ,
 "FileSize": 18566,
 "FileTransferTime": 0.0056,
 "time": "15/12/2021 13:49:08",
 "Encryption time": 0,
},
{
 " Name ": "Save 1",
 "FileSource": "C:/Users/Hanton/Desktop/Tout/CESI/ASSOS\log.json",
 "FileTarget": "C:/Users/Hanton/Desktop/Tout/CESI/A1\log.json",
 "destPath": '' ,
 "FileSize": 875672,
 "FileTransferTime": 0.0057,
 "time": "15/12/2021 13:57:45",
 "Encryption time": 0.0063,
},
{
 " Name ": "Save 1",
 "FileSource": "C:/Users/Hanton/Desktop/Tout/CESI/ASSOS\logIRT.json",
 "FileTarget": "C:/Users/Hanton/Desktop/Tout/CESI/A1\logIRT.json",
 "destPath": '' ,
 "FileSize": 150,
 "FileTransferTime": 0.0066,
 "time": "15/12/2021 13:57:45",
 "Encryption time": 0.0054,
},
{
 " Name ": "Save 1",
 "FileSource": "C:/Users/Hanton/Desktop/Tout/CESI/ASSOS\message.txt",
 "FileTarget": "C:/Users/Hanton/Desktop/Tout/CESI/A1\message.txt",
 "destPath": '' ,
 "FileSize": 1276232,
 "FileTransferTime": 0.0053,
 "time": "15/12/2021 13:57:45",
 "Encryption time": 0,
},
{
 " Name ": "Save 1",
 "FileSource": "C:/Users/Hanton/Desktop/Tout/CESI/ASSOS\Need for Speed - Underground (Europe) (En,Fr,De,Es,It,Nl,Sv).iso",
 "FileTarget": "C:/Users/Hanton/Desktop/Tout/CESI/A1\Need for Speed - Underground (Europe) (En,Fr,De,Es,It,Nl,Sv).iso",
 "destPath": '' ,
 "FileSize": 2726166528,
 "FileTransferTime": 0.0043,
 "time": "15/12/2021 13:57:50",
 "Encryption time": ,
},
{
 " Name ": "Save 1",
 "FileSource": "C:/Users/Hanton/Desktop/Tout/CESI/ASSOS\log.json",
 "FileTarget": "C:/Users/Hanton/Desktop/Tout/CESI/A1\log.json",
 "destPath": '' ,
 "FileSize": 875672,
 "FileTransferTime": 0.0431,
 "time": "15/12/2021 14:37:45",
 "Encryption time": 0,
},
{
 " Name ": "Save 1",
 "FileSource": "C:/Users/Hanton/Desktop/Tout/CESI/ASSOS\logIRT.json",
 "FileTarget": "C:/Users/Hanton/Desktop/Tout/CESI/A1\logIRT.json",
 "destPath": '' ,
 "FileSize": 150,
 "FileTransferTime": 0.0056,
 "time": "15/12/2021 14:37:45",
 "Encryption time": 0,
},
{
 " Name ": "Save 1",
 "FileSource": "C:/Users/Hanton/Desktop/Tout/CESI/ASSOS\message.txt",
 "FileTarget": "C:/Users/Hanton/Desktop/Tout/CESI/A1\message.txt",
 "destPath": '' ,
 "FileSize": 1276232,
 "FileTransferTime": 0.0074,
 "time": "15/12/2021 14:37:45",
 "Encryption time": 0,
},
{
 " Name ": "Save 1",
 "FileSource": "C:/Users/Hanton/Desktop/Tout/CESI/ASSOS\Need for Speed - Underground (Europe) (En,Fr,De,Es,It,Nl,Sv).iso",
 "FileTarget": "C:/Users/Hanton/Desktop/Tout/CESI/A1\Need for Speed - Underground (Europe) (En,Fr,De,Es,It,Nl,Sv).iso",
 "destPath": '' ,
 "FileSize": 2726166528,
 "FileTransferTime": 0.0075,
 "time": "15/12/2021 14:37:50",
 "Encryption time": ,
},
{
 " Name ": "Save 1",
 "FileSource": "C:/Users/Hanton/Desktop/Tout/CESI/ASSOS\log.json",
 "FileTarget": "C:/Users/Hanton/Desktop/Tout/CESI/A1\log.json",
 "destPath": '' ,
 "FileSize": 875672,
 "FileTransferTime": 0.0071,
 "time": "15/12/2021 14:42:44",
 "Encryption time": 0.0068,
},
{
 " Name ": "Save 1",
 "FileSource": "C:/Users/Hanton/Desktop/Tout/CESI/ASSOS\logIRT.json",
 "FileTarget": "C:/Users/Hanton/Desktop/Tout/CESI/A1\logIRT.json",
 "destPath": '' ,
 "FileSize": 150,
 "FileTransferTime": 0.0127,
 "time": "15/12/2021 14:42:44",
 "Encryption time": 0.0087,
},
{
 " Name ": "Save 1",
 "FileSource": "C:/Users/Hanton/Desktop/Tout/CESI/ASSOS\message.txt",
 "FileTarget": "C:/Users/Hanton/Desktop/Tout/CESI/A1\message.txt",
 "destPath": '' ,
 "FileSize": 1276232,
 "FileTransferTime": 0.0138,
 "time": "15/12/2021 14:42:44",
 "Encryption time": 0,
},
{
 " Name ": "Save 1",
 "FileSource": "C:/Users/Hanton/Desktop/Tout/CESI/ASSOS\Papier banque.pdf",
 "FileTarget": "C:/Users/Hanton/Desktop/Tout/CESI/A1\Papier banque.pdf",
 "destPath": '' ,
 "FileSize": 478403,
 "FileTransferTime": 0.009,
 "time": "15/12/2021 14:42:44",
 "Encryption time": 0,
},
{
 " Name ": "Save 1",
 "FileSource": "C:/Users/Hanton/Desktop/Tout/CESI/ASSOS\Papier_banque_vf.pdf",
 "FileTarget": "C:/Users/Hanton/Desktop/Tout/CESI/A1\Papier_banque_vf.pdf",
 "destPath": '' ,
 "FileSize": 789728,
 "FileTransferTime": 0.0083,
 "time": "15/12/2021 14:42:44",
 "Encryption time": 0,
},
{
 " Name ": "Save 1",
 "FileSource": "C:/Users/Hanton/Desktop/Tout/CESI/ASSOS\test.json",
 "FileTarget": "C:/Users/Hanton/Desktop/Tout/CESI/A1\test.json",
 "destPath": '' ,
 "FileSize": 153,
 "FileTransferTime": 0.014,
 "time": "15/12/2021 14:42:44",
 "Encryption time": 0.0117,
},
{
 " Name ": "Save 1",
 "FileSource": "C:/Users/Hanton/Desktop/Tout/CESI/ASSOS\Cresi Racing\Texte.docx",
 "FileTarget": "C:/Users/Hanton/Desktop/Tout/CESI/A1\Cresi Racing\Texte.docx",
 "destPath": '' ,
 "FileSize": 29397,
 "FileTransferTime": 0.0079,
 "time": "15/12/2021 14:42:45",
 "Encryption time": 0,
},
{
 " Name ": "Save 1",
 "FileSource": "C:/Users/Hanton/Desktop/Tout/CESI/ASSOS\JDR\fiche perso Ganir TES.docx",
 "FileTarget": "C:/Users/Hanton/Desktop/Tout/CESI/A1\JDR\fiche perso Ganir TES.docx",
 "destPath": '' ,
 "FileSize": 1876866,
 "FileTransferTime": 0.0085,
 "time": "15/12/2021 14:42:45",
 "Encryption time": 0,
},
{
 " Name ": "Save 1",
 "FileSource": "C:/Users/Hanton/Desktop/Tout/CESI/ASSOS\Sport\message.txt",
 "FileTarget": "C:/Users/Hanton/Desktop/Tout/CESI/A1\Sport\message.txt",
 "destPath": '' ,
 "FileSize": 1276232,
 "FileTransferTime": 0.0068,
 "time": "15/12/2021 14:42:45",
 "Encryption time": 0,
},
{
 " Name ": "Save 1",
 "FileSource": "C:/Users/Hanton/Desktop/Tout/CESI/ASSOS\Sport\Projet CESI SPORT.docx",
 "FileTarget": "C:/Users/Hanton/Desktop/Tout/CESI/A1\Sport\Projet CESI SPORT.docx",
 "destPath": '' ,
 "FileSize": 2293225,
 "FileTransferTime": 0.0048,
 "time": "15/12/2021 14:42:45",
 "Encryption time": 0,
},
{
 " Name ": "Save 1",
 "FileSource": "C:/Users/Hanton/Desktop/Tout/CESI/ASSOS\Wild box\message.txt",
 "FileTarget": "C:/Users/Hanton/Desktop/Tout/CESI/A1\Wild box\message.txt",
 "destPath": '' ,
 "FileSize": 1276232,
 "FileTransferTime": 0.0059,
 "time": "15/12/2021 14:42:45",
 "Encryption time": 0,
},
{
 " Name ": "Save 1",
 "FileSource": "C:/Users/Hanton/Desktop/Tout/CESI/ASSOS\Wild box\CROPS Saver\carotte4.png",
 "FileTarget": "C:/Users/Hanton/Desktop/Tout/CESI/A1\Wild box\CROPS Saver\carotte4.png",
 "destPath": '' ,
 "FileSize": 1618473,
 "FileTransferTime": 0.0055,
 "time": "15/12/2021 14:42:46",
 "Encryption time": 0,
},
{
 " Name ": "Save 1",
 "FileSource": "C:/Users/Hanton/Desktop/Tout/CESI/ASSOS\Wild box\CROPS Saver\Projectile.png",
 "FileTarget": "C:/Users/Hanton/Desktop/Tout/CESI/A1\Wild box\CROPS Saver\Projectile.png",
 "destPath": '' ,
 "FileSize": 372,
 "FileTransferTime": 0.0073,
 "time": "15/12/2021 14:42:46",
 "Encryption time": 0,
},
{
 " Name ": "Save 1",
 "FileSource": "C:/Users/Hanton/Desktop/Tout/CESI/ASSOS\Wild box\Projet solo\Stratégie tour par tour en 1v1.docx",
 "FileTarget": "C:/Users/Hanton/Desktop/Tout/CESI/A1\Wild box\Projet solo\Stratégie tour par tour en 1v1.docx",
 "destPath": '' ,
 "FileSize": 25719,
 "FileTransferTime": 0.0057,
 "time": "15/12/2021 14:42:46",
 "Encryption time": 0,
},
{
 " Name ": "Save 1",
 "FileSource": "C:/Users/Hanton/Desktop/Tout/CESI/ASSOS\Wild box\Projet solo\test map.tmx",
 "FileTarget": "C:/Users/Hanton/Desktop/Tout/CESI/A1\Wild box\Projet solo\test map.tmx",
 "destPath": '' ,
 "FileSize": 20552,
 "FileTransferTime": 0.0056,
 "time": "15/12/2021 14:42:46",
 "Encryption time": 0,
},
{
 " Name ": "Save 1",
 "FileSource": "C:/Users/Hanton/Desktop/Tout/CESI/ASSOS\Wild box\Images\Hanton\Hanton black box.png",
 "FileTarget": "C:/Users/Hanton/Desktop/Tout/CESI/A1\Wild box\Images\Hanton\Hanton black box.png",
 "destPath": '' ,
 "FileSize": 18654,
 "FileTransferTime": 0.0061,
 "time": "15/12/2021 14:42:46",
 "Encryption time": 0,
},
{
 " Name ": "Save 1",
 "FileSource": "C:/Users/Hanton/Desktop/Tout/CESI/ASSOS\Wild box\Images\Hanton\Hanton Pixel Perfect.png",
 "FileTarget": "C:/Users/Hanton/Desktop/Tout/CESI/A1\Wild box\Images\Hanton\Hanton Pixel Perfect.png",
 "destPath": '' ,
 "FileSize": 528,
 "FileTransferTime": 0.012,
 "time": "15/12/2021 14:42:46",
 "Encryption time": 0,
},
{
 " Name ": "Save 1",
 "FileSource": "C:/Users/Hanton/Desktop/Tout/CESI/ASSOS\Wild box\Images\Hanton\Hanton white box.png",
 "FileTarget": "C:/Users/Hanton/Desktop/Tout/CESI/A1\Wild box\Images\Hanton\Hanton white box.png",
 "destPath": '' ,
 "FileSize": 18566,
 "FileTransferTime": 0.0054,
 "time": "15/12/2021 14:42:46",
 "Encryption time": 0,
},
{
 " Name ": "Save 1",
 "FileSource": "C:/Users/Hanton/Desktop/Tout/CESI/ASSOS\log.json",
 "FileTarget": "C:/Users/Hanton/Desktop/Tout/CESI/A1\log.json",
 "destPath": '' ,
 "FileSize": 875672,
 "FileTransferTime": 0.0046,
 "time": "15/12/2021 14:46:36",
 "Encryption time": 0.0051,
},
{
 " Name ": "Save 1",
 "FileSource": "C:/Users/Hanton/Desktop/Tout/CESI/ASSOS\logIRT.json",
 "FileTarget": "C:/Users/Hanton/Desktop/Tout/CESI/A1\logIRT.json",
 "destPath": '' ,
 "FileSize": 150,
 "FileTransferTime": 0.0042,
 "time": "15/12/2021 14:46:36",
 "Encryption time": 0.0049,
},
{
 " Name ": "Save 1",
 "FileSource": "C:/Users/Hanton/Desktop/Tout/CESI/ASSOS\message.txt",
 "FileTarget": "C:/Users/Hanton/Desktop/Tout/CESI/A1\message.txt",
 "destPath": '' ,
 "FileSize": 1276232,
 "FileTransferTime": 0.0051,
 "time": "15/12/2021 14:46:36",
 "Encryption time": 0,
},
{
 " Name ": "Save 1",
 "FileSource": "C:/Users/Hanton/Desktop/Tout/CESI/ASSOS\Papier banque.pdf",
 "FileTarget": "C:/Users/Hanton/Desktop/Tout/CESI/A1\Papier banque.pdf",
 "destPath": '' ,
 "FileSize": 478403,
 "FileTransferTime": 0.004,
 "time": "15/12/2021 14:47:13",
 "Encryption time": 0,
},
{
 " Name ": "Save 1",
 "FileSource": "C:/Users/Hanton/Desktop/Tout/CESI/ASSOS\Papier_banque_vf.pdf",
 "FileTarget": "C:/Users/Hanton/Desktop/Tout/CESI/A1\Papier_banque_vf.pdf",
 "destPath": '' ,
 "FileSize": 789728,
 "FileTransferTime": 0.0043,
 "time": "15/12/2021 14:47:13",
 "Encryption time": 0,
},
{
 " Name ": "Save 1",
 "FileSource": "C:/Users/Hanton/Desktop/Tout/CESI/ASSOS\test.json",
 "FileTarget": "C:/Users/Hanton/Desktop/Tout/CESI/A1\test.json",
 "destPath": '' ,
 "FileSize": 153,
 "FileTransferTime": 0.0051,
 "time": "15/12/2021 14:47:13",
 "Encryption time": 0.0047,
},
{
 " Name ": "Save 1",
 "FileSource": "C:/Users/Hanton/Desktop/Tout/CESI/ASSOS\log.json",
 "FileTarget": "C:/Users/Hanton/Desktop/Tout/CESI/A1\log.json",
 "destPath": '' ,
 "FileSize": 875672,
 "FileTransferTime": 0.0056,
 "time": "15/12/2021 14:47:20",
 "Encryption time": 0.0048,
},
{
 " Name ": "Save 1",
 "FileSource": "C:/Users/Hanton/Desktop/Tout/CESI/ASSOS\logIRT.json",
 "FileTarget": "C:/Users/Hanton/Desktop/Tout/CESI/A1\logIRT.json",
 "destPath": '' ,
 "FileSize": 150,
 "FileTransferTime": 0.0074,
 "time": "15/12/2021 14:47:20",
 "Encryption time": 0.0058,
},
{
 " Name ": "Save 1",
 "FileSource": "C:/Users/Hanton/Desktop/Tout/CESI/ASSOS\message.txt",
 "FileTarget": "C:/Users/Hanton/Desktop/Tout/CESI/A1\message.txt",
 "destPath": '' ,
 "FileSize": 1276232,
 "FileTransferTime": 0.005,
 "time": "15/12/2021 14:47:20",
 "Encryption time": 0,
},
{
 " Name ": "Save 1",
 "FileSource": "C:/Users/Hanton/Desktop/Tout/CESI/ASSOS\Papier banque.pdf",
 "FileTarget": "C:/Users/Hanton/Desktop/Tout/CESI/A1\Papier banque.pdf",
 "destPath": '' ,
 "FileSize": 478403,
 "FileTransferTime": 0.0051,
 "time": "15/12/2021 14:47:22",
 "Encryption time": 0,
},
{
 " Name ": "Save 1",
 "FileSource": "C:/Users/Hanton/Desktop/Tout/CESI/ASSOS\Papier_banque_vf.pdf",
 "FileTarget": "C:/Users/Hanton/Desktop/Tout/CESI/A1\Papier_banque_vf.pdf",
 "destPath": '' ,
 "FileSize": 789728,
 "FileTransferTime": 0.0049,
 "time": "15/12/2021 14:47:22",
 "Encryption time": 0,
},
{
 " Name ": "Save 1",
 "FileSource": "C:/Users/Hanton/Desktop/Tout/CESI/ASSOS\test.json",
 "FileTarget": "C:/Users/Hanton/Desktop/Tout/CESI/A1\test.json",
 "destPath": '' ,
 "FileSize": 153,
 "FileTransferTime": 0.0053,
 "time": "15/12/2021 14:47:22",
 "Encryption time": 0.0066,
},
{
 " Name ": "Save 1",
 "FileSource": "C:/Users/Hanton/Desktop/Tout/CESI/ASSOS\Cresi Racing\Texte.docx",
 "FileTarget": "C:/Users/Hanton/Desktop/Tout/CESI/A1\Cresi Racing\Texte.docx",
 "destPath": '' ,
 "FileSize": 29397,
 "FileTransferTime": 0.0102,
 "time": "15/12/2021 14:47:22",
 "Encryption time": 0,
},
{
 " Name ": "Save 1",
 "FileSource": "C:/Users/Hanton/Desktop/Tout/CESI/ASSOS\JDR\fiche perso Ganir TES.docx",
 "FileTarget": "C:/Users/Hanton/Desktop/Tout/CESI/A1\JDR\fiche perso Ganir TES.docx",
 "destPath": '' ,
 "FileSize": 1876866,
 "FileTransferTime": 0.0061,
 "time": "15/12/2021 14:47:22",
 "Encryption time": 0,
},
{
 " Name ": "Save 1",
 "FileSource": "C:/Users/Hanton/Desktop/Tout/CESI/ASSOS\Sport\message.txt",
 "FileTarget": "C:/Users/Hanton/Desktop/Tout/CESI/A1\Sport\message.txt",
 "destPath": '' ,
 "FileSize": 1276232,
 "FileTransferTime": 0.0052,
 "time": "15/12/2021 14:47:23",
 "Encryption time": 0,
},
{
 " Name ": "Save 1",
 "FileSource": "C:/Users/Hanton/Desktop/Tout/CESI/ASSOS\Sport\Projet CESI SPORT.docx",
 "FileTarget": "C:/Users/Hanton/Desktop/Tout/CESI/A1\Sport\Projet CESI SPORT.docx",
 "destPath": '' ,
 "FileSize": 2293225,
 "FileTransferTime": 0.0068,
 "time": "15/12/2021 14:47:23",
 "Encryption time": 0,
},
{
 " Name ": "Save 1",
 "FileSource": "C:/Users/Hanton/Desktop/Tout/CESI/ASSOS\Wild box\message.txt",
 "FileTarget": "C:/Users/Hanton/Desktop/Tout/CESI/A1\Wild box\message.txt",
 "destPath": '' ,
 "FileSize": 1276232,
 "FileTransferTime": 0.0056,
 "time": "15/12/2021 14:47:23",
 "Encryption time": 0,
},
{
 " Name ": "Save 1",
 "FileSource": "C:/Users/Hanton/Desktop/Tout/CESI/ASSOS\Wild box\CROPS Saver\carotte4.png",
 "FileTarget": "C:/Users/Hanton/Desktop/Tout/CESI/A1\Wild box\CROPS Saver\carotte4.png",
 "destPath": '' ,
 "FileSize": 1618473,
 "FileTransferTime": 0.0059,
 "time": "15/12/2021 14:47:23",
 "Encryption time": 0,
},
{
 " Name ": "Save 1",
 "FileSource": "C:/Users/Hanton/Desktop/Tout/CESI/ASSOS\Wild box\CROPS Saver\Projectile.png",
 "FileTarget": "C:/Users/Hanton/Desktop/Tout/CESI/A1\Wild box\CROPS Saver\Projectile.png",
 "destPath": '' ,
 "FileSize": 372,
 "FileTransferTime": 0.0052,
 "time": "15/12/2021 14:47:24",
 "Encryption time": 0,
},
{
 " Name ": "Save 1",
 "FileSource": "C:/Users/Hanton/Desktop/Tout/CESI/ASSOS\Wild box\Projet solo\Stratégie tour par tour en 1v1.docx",
 "FileTarget": "C:/Users/Hanton/Desktop/Tout/CESI/A1\Wild box\Projet solo\Stratégie tour par tour en 1v1.docx",
 "destPath": '' ,
 "FileSize": 25719,
 "FileTransferTime": 0.0196,
 "time": "15/12/2021 14:47:24",
 "Encryption time": 0,
},
{
 " Name ": "Save 1",
 "FileSource": "C:/Users/Hanton/Desktop/Tout/CESI/ASSOS\Wild box\Projet solo\test map.tmx",
 "FileTarget": "C:/Users/Hanton/Desktop/Tout/CESI/A1\Wild box\Projet solo\test map.tmx",
 "destPath": '' ,
 "FileSize": 20552,
 "FileTransferTime": 0.0053,
 "time": "15/12/2021 14:47:24",
 "Encryption time": 0,
},
{
 " Name ": "Save 1",
 "FileSource": "C:/Users/Hanton/Desktop/Tout/CESI/ASSOS\Wild box\Images\Hanton\Hanton black box.png",
 "FileTarget": "C:/Users/Hanton/Desktop/Tout/CESI/A1\Wild box\Images\Hanton\Hanton black box.png",
 "destPath": '' ,
 "FileSize": 18654,
 "FileTransferTime": 0.0054,
 "time": "15/12/2021 14:47:24",
 "Encryption time": 0,
},
{
 " Name ": "Save 1",
 "FileSource": "C:/Users/Hanton/Desktop/Tout/CESI/ASSOS\Wild box\Images\Hanton\Hanton Pixel Perfect.png",
 "FileTarget": "C:/Users/Hanton/Desktop/Tout/CESI/A1\Wild box\Images\Hanton\Hanton Pixel Perfect.png",
 "destPath": '' ,
 "FileSize": 528,
 "FileTransferTime": 0.0074,
 "time": "15/12/2021 14:47:24",
 "Encryption time": 0,
},
{
 " Name ": "Save 1",
 "FileSource": "C:/Users/Hanton/Desktop/Tout/CESI/ASSOS\Wild box\Images\Hanton\Hanton white box.png",
 "FileTarget": "C:/Users/Hanton/Desktop/Tout/CESI/A1\Wild box\Images\Hanton\Hanton white box.png",
 "destPath": '' ,
 "FileSize": 18566,
 "FileTransferTime": 0.0055,
 "time": "15/12/2021 14:47:24",
 "Encryption time": 0,
},
{
 " Name ": "Save 1",
 "FileSource": "C:/Users/Hanton/Desktop/Tout/CESI/ASSOS\log.json",
 "FileTarget": "C:/Users/Hanton/Desktop/Tout/CESI/A1\log.json",
 "destPath": '' ,
 "FileSize": 875672,
 "FileTransferTime": 0.0042,
 "time": "15/12/2021 14:48:22",
 "Encryption time": 0.0059,
},
{
 " Name ": "Save 1",
 "FileSource": "C:/Users/Hanton/Desktop/Tout/CESI/ASSOS\logIRT.json",
 "FileTarget": "C:/Users/Hanton/Desktop/Tout/CESI/A1\logIRT.json",
 "destPath": '' ,
 "FileSize": 150,
 "FileTransferTime": 0.0049,
 "time": "15/12/2021 14:48:22",
 "Encryption time": 0.0051,
},
{
 " Name ": "Save 1",
 "FileSource": "C:/Users/Hanton/Desktop/Tout/CESI/ASSOS\message.txt",
 "FileTarget": "C:/Users/Hanton/Desktop/Tout/CESI/A1\message.txt",
 "destPath": '' ,
 "FileSize": 1276232,
 "FileTransferTime": 0.0052,
 "time": "15/12/2021 14:48:22",
 "Encryption time": 0,
},
{
 " Name ": "Save 1",
 "FileSource": "C:/Users/Hanton/Desktop/Tout/CESI/ASSOS\Papier banque.pdf",
 "FileTarget": "C:/Users/Hanton/Desktop/Tout/CESI/A1\Papier banque.pdf",
 "destPath": '' ,
 "FileSize": 478403,
 "FileTransferTime": 0.0044,
 "time": "15/12/2021 14:48:27",
 "Encryption time": 0,
},
{
 " Name ": "Save 1",
 "FileSource": "C:/Users/Hanton/Desktop/Tout/CESI/ASSOS\Papier_banque_vf.pdf",
 "FileTarget": "C:/Users/Hanton/Desktop/Tout/CESI/A1\Papier_banque_vf.pdf",
 "destPath": '' ,
 "FileSize": 789728,
 "FileTransferTime": 0.0044,
 "time": "15/12/2021 14:48:27",
 "Encryption time": 0,
},
{
 " Name ": "Save 1",
 "FileSource": "C:/Users/Hanton/Desktop/Tout/CESI/ASSOS\test.json",
 "FileTarget": "C:/Users/Hanton/Desktop/Tout/CESI/A1\test.json",
 "destPath": '' ,
 "FileSize": 153,
 "FileTransferTime": 0.0043,
 "time": "15/12/2021 14:48:27",
 "Encryption time": 0.0059,
},
{
 " Name ": "Save 1",
 "FileSource": "C:/Users/Hanton/Desktop/Tout/CESI/ASSOS\Cresi Racing\Texte.docx",
 "FileTarget": "C:/Users/Hanton/Desktop/Tout/CESI/A1\Cresi Racing\Texte.docx",
 "destPath": '' ,
 "FileSize": 29397,
 "FileTransferTime": 0.0053,
 "time": "15/12/2021 14:48:27",
 "Encryption time": 0,
},
{
 " Name ": "Save 1",
 "FileSource": "C:/Users/Hanton/Desktop/Tout/CESI/ASSOS\JDR\fiche perso Ganir TES.docx",
 "FileTarget": "C:/Users/Hanton/Desktop/Tout/CESI/A1\JDR\fiche perso Ganir TES.docx",
 "destPath": '' ,
 "FileSize": 1876866,
 "FileTransferTime": 0.0069,
 "time": "15/12/2021 14:48:27",
 "Encryption time": 0,
},
{
 " Name ": "Save 1",
 "FileSource": "C:/Users/Hanton/Desktop/Tout/CESI/ASSOS\Sport\message.txt",
 "FileTarget": "C:/Users/Hanton/Desktop/Tout/CESI/A1\Sport\message.txt",
 "destPath": '' ,
 "FileSize": 1276232,
 "FileTransferTime": 0.0055,
 "time": "15/12/2021 14:48:28",
 "Encryption time": 0,
},
{
 " Name ": "Save 1",
 "FileSource": "C:/Users/Hanton/Desktop/Tout/CESI/ASSOS\Sport\Projet CESI SPORT.docx",
 "FileTarget": "C:/Users/Hanton/Desktop/Tout/CESI/A1\Sport\Projet CESI SPORT.docx",
 "destPath": '' ,
 "FileSize": 2293225,
 "FileTransferTime": 0.0061,
 "time": "15/12/2021 14:48:28",
 "Encryption time": 0,
},
{
 " Name ": "Save 1",
 "FileSource": "C:/Users/Hanton/Desktop/Tout/CESI/ASSOS\Wild box\message.txt",
 "FileTarget": "C:/Users/Hanton/Desktop/Tout/CESI/A1\Wild box\message.txt",
 "destPath": '' ,
 "FileSize": 1276232,
 "FileTransferTime": 0.0053,
 "time": "15/12/2021 14:48:28",
 "Encryption time": 0,
},
{
 " Name ": "Save 1",
 "FileSource": "C:/Users/Hanton/Desktop/Tout/CESI/ASSOS\Wild box\CROPS Saver\carotte4.png",
 "FileTarget": "C:/Users/Hanton/Desktop/Tout/CESI/A1\Wild box\CROPS Saver\carotte4.png",
 "destPath": '' ,
 "FileSize": 1618473,
 "FileTransferTime": 0.0048,
 "time": "15/12/2021 14:48:28",
 "Encryption time": 0,
},
{
 " Name ": "Save 1",
 "FileSource": "C:/Users/Hanton/Desktop/Tout/CESI/ASSOS\Wild box\CROPS Saver\Projectile.png",
 "FileTarget": "C:/Users/Hanton/Desktop/Tout/CESI/A1\Wild box\CROPS Saver\Projectile.png",
 "destPath": '' ,
 "FileSize": 372,
 "FileTransferTime": 0.0061,
 "time": "15/12/2021 14:48:28",
 "Encryption time": 0,
},
{
 " Name ": "Save 1",
 "FileSource": "C:/Users/Hanton/Desktop/Tout/CESI/ASSOS\Wild box\Projet solo\Stratégie tour par tour en 1v1.docx",
 "FileTarget": "C:/Users/Hanton/Desktop/Tout/CESI/A1\Wild box\Projet solo\Stratégie tour par tour en 1v1.docx",
 "destPath": '' ,
 "FileSize": 25719,
 "FileTransferTime": 0.0068,
 "time": "15/12/2021 14:48:28",
 "Encryption time": 0,
},
{
 " Name ": "Save 1",
 "FileSource": "C:/Users/Hanton/Desktop/Tout/CESI/ASSOS\Wild box\Projet solo\test map.tmx",
 "FileTarget": "C:/Users/Hanton/Desktop/Tout/CESI/A1\Wild box\Projet solo\test map.tmx",
 "destPath": '' ,
 "FileSize": 20552,
 "FileTransferTime": 0.0053,
 "time": "15/12/2021 14:48:29",
 "Encryption time": 0,
},
{
 " Name ": "Save 1",
 "FileSource": "C:/Users/Hanton/Desktop/Tout/CESI/ASSOS\Wild box\Images\Hanton\Hanton black box.png",
 "FileTarget": "C:/Users/Hanton/Desktop/Tout/CESI/A1\Wild box\Images\Hanton\Hanton black box.png",
 "destPath": '' ,
 "FileSize": 18654,
 "FileTransferTime": 0.0059,
 "time": "15/12/2021 14:48:29",
 "Encryption time": 0,
},
{
 " Name ": "Save 1",
 "FileSource": "C:/Users/Hanton/Desktop/Tout/CESI/ASSOS\Wild box\Images\Hanton\Hanton Pixel Perfect.png",
 "FileTarget": "C:/Users/Hanton/Desktop/Tout/CESI/A1\Wild box\Images\Hanton\Hanton Pixel Perfect.png",
 "destPath": '' ,
 "FileSize": 528,
 "FileTransferTime": 0.0058,
 "time": "15/12/2021 14:48:29",
 "Encryption time": 0,
},
{
 " Name ": "Save 1",
 "FileSource": "C:/Users/Hanton/Desktop/Tout/CESI/ASSOS\Wild box\Images\Hanton\Hanton white box.png",
 "FileTarget": "C:/Users/Hanton/Desktop/Tout/CESI/A1\Wild box\Images\Hanton\Hanton white box.png",
 "destPath": '' ,
 "FileSize": 18566,
 "FileTransferTime": 0.0056,
 "time": "15/12/2021 14:48:29",
 "Encryption time": 0,
},
{
 " Name ": "Save 1",
 "FileSource": "C:/Users/Hanton/Desktop/Tout/CESI/ASSOS\log.json",
 "FileTarget": "C:/Users/Hanton/Desktop/Tout/CESI/A1\log.json",
 "destPath": '' ,
 "FileSize": 875672,
 "FileTransferTime": 0.005,
 "time": "15/12/2021 14:49:05",
 "Encryption time": 0.0049,
},
{
 " Name ": "Save 1",
 "FileSource": "C:/Users/Hanton/Desktop/Tout/CESI/ASSOS\logIRT.json",
 "FileTarget": "C:/Users/Hanton/Desktop/Tout/CESI/A1\logIRT.json",
 "destPath": '' ,
 "FileSize": 150,
 "FileTransferTime": 0.0046,
 "time": "15/12/2021 14:49:05",
 "Encryption time": 0.0072,
},
{
 " Name ": "Save 1",
 "FileSource": "C:/Users/Hanton/Desktop/Tout/CESI/ASSOS\message.txt",
 "FileTarget": "C:/Users/Hanton/Desktop/Tout/CESI/A1\message.txt",
 "destPath": '' ,
 "FileSize": 1276232,
 "FileTransferTime": 0.0056,
 "time": "15/12/2021 14:49:05",
 "Encryption time": 0,
},
{
 " Name ": "Save 1",
 "FileSource": "C:/Users/Hanton/Desktop/Tout/CESI/ASSOS\Papier banque.pdf",
 "FileTarget": "C:/Users/Hanton/Desktop/Tout/CESI/A1\Papier banque.pdf",
 "destPath": '' ,
 "FileSize": 478403,
 "FileTransferTime": 0.0045,
 "time": "15/12/2021 14:49:08",
 "Encryption time": 0,
},
{
 " Name ": "Save 1",
 "FileSource": "C:/Users/Hanton/Desktop/Tout/CESI/ASSOS\Papier_banque_vf.pdf",
 "FileTarget": "C:/Users/Hanton/Desktop/Tout/CESI/A1\Papier_banque_vf.pdf",
 "destPath": '' ,
 "FileSize": 789728,
 "FileTransferTime": 0.0048,
 "time": "15/12/2021 14:49:08",
 "Encryption time": 0,
},
{
 " Name ": "Save 1",
 "FileSource": "C:/Users/Hanton/Desktop/Tout/CESI/ASSOS\test.json",
 "FileTarget": "C:/Users/Hanton/Desktop/Tout/CESI/A1\test.json",
 "destPath": '' ,
 "FileSize": 153,
 "FileTransferTime": 0.0044,
 "time": "15/12/2021 14:49:08",
 "Encryption time": 0.0056,
},
{
 " Name ": "Save 1",
 "FileSource": "C:/Users/Hanton/Desktop/Tout/CESI/ASSOS\Cresi Racing\Texte.docx",
 "FileTarget": "C:/Users/Hanton/Desktop/Tout/CESI/A1\Cresi Racing\Texte.docx",
 "destPath": '' ,
 "FileSize": 29397,
 "FileTransferTime": 0.0051,
 "time": "15/12/2021 14:49:08",
 "Encryption time": 0,
},
{
 " Name ": "Save 1",
 "FileSource": "C:/Users/Hanton/Desktop/Tout/CESI/ASSOS\JDR\fiche perso Ganir TES.docx",
 "FileTarget": "C:/Users/Hanton/Desktop/Tout/CESI/A1\JDR\fiche perso Ganir TES.docx",
 "destPath": '' ,
 "FileSize": 1876866,
 "FileTransferTime": 0.0057,
 "time": "15/12/2021 14:49:08",
 "Encryption time": 0,
},
{
 " Name ": "Save 1",
 "FileSource": "C:/Users/Hanton/Desktop/Tout/CESI/ASSOS\Sport\message.txt",
 "FileTarget": "C:/Users/Hanton/Desktop/Tout/CESI/A1\Sport\message.txt",
 "destPath": '' ,
 "FileSize": 1276232,
 "FileTransferTime": 0.0062,
 "time": "15/12/2021 14:49:08",
 "Encryption time": 0,
},
{
 " Name ": "Save 1",
 "FileSource": "C:/Users/Hanton/Desktop/Tout/CESI/ASSOS\Sport\Projet CESI SPORT.docx",
 "FileTarget": "C:/Users/Hanton/Desktop/Tout/CESI/A1\Sport\Projet CESI SPORT.docx",
 "destPath": '' ,
 "FileSize": 2293225,
 "FileTransferTime": 0.0056,
 "time": "15/12/2021 14:49:08",
 "Encryption time": 0,
},
{
 " Name ": "Save 1",
 "FileSource": "C:/Users/Hanton/Desktop/Tout/CESI/ASSOS\Wild box\message.txt",
 "FileTarget": "C:/Users/Hanton/Desktop/Tout/CESI/A1\Wild box\message.txt",
 "destPath": '' ,
 "FileSize": 1276232,
 "FileTransferTime": 0.0054,
 "time": "15/12/2021 14:49:08",
 "Encryption time": 0,
},
{
 " Name ": "Save 1",
 "FileSource": "C:/Users/Hanton/Desktop/Tout/CESI/ASSOS\Wild box\CROPS Saver\carotte4.png",
 "FileTarget": "C:/Users/Hanton/Desktop/Tout/CESI/A1\Wild box\CROPS Saver\carotte4.png",
 "destPath": '' ,
 "FileSize": 1618473,
 "FileTransferTime": 0.0062,
 "time": "15/12/2021 14:49:09",
 "Encryption time": 0,
},
{
 " Name ": "Save 1",
 "FileSource": "C:/Users/Hanton/Desktop/Tout/CESI/ASSOS\Wild box\CROPS Saver\Projectile.png",
 "FileTarget": "C:/Users/Hanton/Desktop/Tout/CESI/A1\Wild box\CROPS Saver\Projectile.png",
 "destPath": '' ,
 "FileSize": 372,
 "FileTransferTime": 0.0062,
 "time": "15/12/2021 14:49:09",
 "Encryption time": 0,
},
{
 " Name ": "Save 1",
 "FileSource": "C:/Users/Hanton/Desktop/Tout/CESI/ASSOS\Wild box\Projet solo\Stratégie tour par tour en 1v1.docx",
 "FileTarget": "C:/Users/Hanton/Desktop/Tout/CESI/A1\Wild box\Projet solo\Stratégie tour par tour en 1v1.docx",
 "destPath": '' ,
 "FileSize": 25719,
 "FileTransferTime": 0.0063,
 "time": "15/12/2021 14:49:09",
 "Encryption time": 0,
},
{
 " Name ": "Save 1",
 "FileSource": "C:/Users/Hanton/Desktop/Tout/CESI/ASSOS\Wild box\Projet solo\test map.tmx",
 "FileTarget": "C:/Users/Hanton/Desktop/Tout/CESI/A1\Wild box\Projet solo\test map.tmx",
 "destPath": '' ,
 "FileSize": 20552,
 "FileTransferTime": 0.0063,
 "time": "15/12/2021 14:49:09",
 "Encryption time": 0,
},
{
 " Name ": "Save 1",
 "FileSource": "C:/Users/Hanton/Desktop/Tout/CESI/ASSOS\Wild box\Images\Hanton\Hanton black box.png",
 "FileTarget": "C:/Users/Hanton/Desktop/Tout/CESI/A1\Wild box\Images\Hanton\Hanton black box.png",
 "destPath": '' ,
 "FileSize": 18654,
 "FileTransferTime": 0.005,
 "time": "15/12/2021 14:49:09",
 "Encryption time": 0,
},
{
 " Name ": "Save 1",
 "FileSource": "C:/Users/Hanton/Desktop/Tout/CESI/ASSOS\Wild box\Images\Hanton\Hanton Pixel Perfect.png",
 "FileTarget": "C:/Users/Hanton/Desktop/Tout/CESI/A1\Wild box\Images\Hanton\Hanton Pixel Perfect.png",
 "destPath": '' ,
 "FileSize": 528,
 "FileTransferTime": 0.0054,
 "time": "15/12/2021 14:49:09",
 "Encryption time": 0,
},
{
 " Name ": "Save 1",
 "FileSource": "C:/Users/Hanton/Desktop/Tout/CESI/ASSOS\Wild box\Images\Hanton\Hanton white box.png",
 "FileTarget": "C:/Users/Hanton/Desktop/Tout/CESI/A1\Wild box\Images\Hanton\Hanton white box.png",
 "destPath": '' ,
 "FileSize": 18566,
 "FileTransferTime": 0.0055,
 "time": "15/12/2021 14:49:09",
 "Encryption time": 0,
},
{
 " Name ": "Save 1",
 "FileSource": "C:/Users/Hanton/Desktop/Tout/CESI/ASSOS\log.json",
 "FileTarget": "C:/Users/Hanton/Desktop/Tout/CESI/A1\log.json",
 "destPath": '' ,
 "FileSize": 875672,
 "FileTransferTime": 0.0069,
 "time": "15/12/2021 15:43:26",
 "Encryption time": ,
},
{
 " Name ": "Save 1",
 "FileSource": "C:/Users/Hanton/Desktop/Tout/CESI/ASSOS\log.json",
 "FileTarget": "C:/Users/Hanton/Desktop/Tout/CESI/A1\log.json",
 "destPath": '' ,
 "FileSize": 875672,
 "FileTransferTime": 0.008,
 "time": "15/12/2021 15:46:10",
 "Encryption time": ,
},
{
 " Name ": "Save 1",
 "FileSource": "C:/Users/Hanton/Desktop/Tout/CESI/ASSOS\log.json",
 "FileTarget": "C:/Users/Hanton/Desktop/Tout/CESI/A1\log.json",
 "destPath": '' ,
 "FileSize": 875672,
 "FileTransferTime": 0.0071,
 "time": "15/12/2021 16:13:02",
 "Encryption time": ,
},
{
 " Name ": "Save 1",
 "FileSource": "C:/Users/Hanton/Desktop/Tout/CESI/ASSOS\logIRT.json",
 "FileTarget": "C:/Users/Hanton/Desktop/Tout/CESI/A1\logIRT.json",
 "destPath": '' ,
 "FileSize": 150,
 "FileTransferTime": 0.0076,
 "time": "15/12/2021 16:13:02",
 "Encryption time": ,
},
{
 " Name ": "Save 1",
 "FileSource": "C:/Users/Hanton/Desktop/Tout/CESI/ASSOS\message.txt",
 "FileTarget": "C:/Users/Hanton/Desktop/Tout/CESI/A1\message.txt",
 "destPath": '' ,
 "FileSize": 1276232,
 "FileTransferTime": 0.0076,
 "time": "15/12/2021 16:13:02",
 "Encryption time": ,
},
{
 " Name ": "Save 1",
 "FileSource": "C:/Users/Hanton/Desktop/Tout/CESI/ASSOS\Papier banque.pdf",
 "FileTarget": "C:/Users/Hanton/Desktop/Tout/CESI/A1\Papier banque.pdf",
 "destPath": '' ,
 "FileSize": 478403,
 "FileTransferTime": 0.0078,
 "time": "15/12/2021 16:13:04",
 "Encryption time": ,
},
{
 " Name ": "Save 1",
 "FileSource": "C:/Users/Hanton/Desktop/Tout/CESI/ASSOS\Papier_banque_vf.pdf",
 "FileTarget": "C:/Users/Hanton/Desktop/Tout/CESI/A1\Papier_banque_vf.pdf",
 "destPath": '' ,
 "FileSize": 789728,
 "FileTransferTime": 0.0066,
 "time": "15/12/2021 16:13:04",
 "Encryption time": ,
},
{
 " Name ": "Save 1",
 "FileSource": "C:/Users/Hanton/Desktop/Tout/CESI/ASSOS\test.json",
 "FileTarget": "C:/Users/Hanton/Desktop/Tout/CESI/A1\test.json",
 "destPath": '' ,
 "FileSize": 153,
 "FileTransferTime": 0.0069,
 "time": "15/12/2021 16:13:04",
 "Encryption time": ,
},
{
 " Name ": "Save 1",
 "FileSource": "C:/Users/Hanton/Desktop/Tout/CESI/ASSOS\Cresi Racing\Texte.docx",
 "FileTarget": "C:/Users/Hanton/Desktop/Tout/CESI/A1\Cresi Racing\Texte.docx",
 "destPath": '' ,
 "FileSize": 29397,
 "FileTransferTime": 0.0067,
 "time": "15/12/2021 16:13:04",
 "Encryption time": ,
},
{
 " Name ": "Save 1",
 "FileSource": "C:/Users/Hanton/Desktop/Tout/CESI/ASSOS\JDR\fiche perso Ganir TES.docx",
 "FileTarget": "C:/Users/Hanton/Desktop/Tout/CESI/A1\JDR\fiche perso Ganir TES.docx",
 "destPath": '' ,
 "FileSize": 1876866,
 "FileTransferTime": 0.0085,
 "time": "15/12/2021 16:13:04",
 "Encryption time": ,
},
{
 " Name ": "Save 1",
 "FileSource": "C:/Users/Hanton/Desktop/Tout/CESI/ASSOS\Sport\message.txt",
 "FileTarget": "C:/Users/Hanton/Desktop/Tout/CESI/A1\Sport\message.txt",
 "destPath": '' ,
 "FileSize": 1276232,
 "FileTransferTime": 0.0071,
 "time": "15/12/2021 16:13:04",
 "Encryption time": ,
},
{
 " Name ": "Save 1",
 "FileSource": "C:/Users/Hanton/Desktop/Tout/CESI/ASSOS\Sport\Projet CESI SPORT.docx",
 "FileTarget": "C:/Users/Hanton/Desktop/Tout/CESI/A1\Sport\Projet CESI SPORT.docx",
 "destPath": '' ,
 "FileSize": 2293225,
 "FileTransferTime": 0.0067,
 "time": "15/12/2021 16:13:04",
 "Encryption time": ,
},
{
 " Name ": "Save 1",
 "FileSource": "C:/Users/Hanton/Desktop/Tout/CESI/ASSOS\Wild box\message.txt",
 "FileTarget": "C:/Users/Hanton/Desktop/Tout/CESI/A1\Wild box\message.txt",
 "destPath": '' ,
 "FileSize": 1276232,
 "FileTransferTime": 0.0049,
 "time": "15/12/2021 16:13:04",
 "Encryption time": ,
},
{
 " Name ": "Save 1",
 "FileSource": "C:/Users/Hanton/Desktop/Tout/CESI/ASSOS\Wild box\CROPS Saver\carotte4.png",
 "FileTarget": "C:/Users/Hanton/Desktop/Tout/CESI/A1\Wild box\CROPS Saver\carotte4.png",
 "destPath": '' ,
 "FileSize": 1618473,
 "FileTransferTime": 0.0047,
 "time": "15/12/2021 16:13:04",
 "Encryption time": ,
},
{
 " Name ": "Save 1",
 "FileSource": "C:/Users/Hanton/Desktop/Tout/CESI/ASSOS\Wild box\CROPS Saver\Projectile.png",
 "FileTarget": "C:/Users/Hanton/Desktop/Tout/CESI/A1\Wild box\CROPS Saver\Projectile.png",
 "destPath": '' ,
 "FileSize": 372,
 "FileTransferTime": 0.0055,
 "time": "15/12/2021 16:13:04",
 "Encryption time": ,
},
{
 " Name ": "Save 1",
 "FileSource": "C:/Users/Hanton/Desktop/Tout/CESI/ASSOS\Wild box\Projet solo\Stratégie tour par tour en 1v1.docx",
 "FileTarget": "C:/Users/Hanton/Desktop/Tout/CESI/A1\Wild box\Projet solo\Stratégie tour par tour en 1v1.docx",
 "destPath": '' ,
 "FileSize": 25719,
 "FileTransferTime": 0.0053,
 "time": "15/12/2021 16:13:04",
 "Encryption time": ,
},
{
 " Name ": "Save 1",
 "FileSource": "C:/Users/Hanton/Desktop/Tout/CESI/ASSOS\Wild box\Projet solo\test map.tmx",
 "FileTarget": "C:/Users/Hanton/Desktop/Tout/CESI/A1\Wild box\Projet solo\test map.tmx",
 "destPath": '' ,
 "FileSize": 20552,
 "FileTransferTime": 0.0045,
 "time": "15/12/2021 16:13:04",
 "Encryption time": ,
},
{
 " Name ": "Save 1",
 "FileSource": "C:/Users/Hanton/Desktop/Tout/CESI/ASSOS\Wild box\Images\Hanton\Hanton black box.png",
 "FileTarget": "C:/Users/Hanton/Desktop/Tout/CESI/A1\Wild box\Images\Hanton\Hanton black box.png",
 "destPath": '' ,
 "FileSize": 18654,
 "FileTransferTime": 0.0042,
 "time": "15/12/2021 16:13:04",
 "Encryption time": ,
},
{
 " Name ": "Save 1",
 "FileSource": "C:/Users/Hanton/Desktop/Tout/CESI/ASSOS\Wild box\Images\Hanton\Hanton Pixel Perfect.png",
 "FileTarget": "C:/Users/Hanton/Desktop/Tout/CESI/A1\Wild box\Images\Hanton\Hanton Pixel Perfect.png",
 "destPath": '' ,
 "FileSize": 528,
 "FileTransferTime": 0.0042,
 "time": "15/12/2021 16:13:04",
 "Encryption time": ,
},
{
 " Name ": "Save 1",
 "FileSource": "C:/Users/Hanton/Desktop/Tout/CESI/ASSOS\Wild box\Images\Hanton\Hanton white box.png",
 "FileTarget": "C:/Users/Hanton/Desktop/Tout/CESI/A1\Wild box\Images\Hanton\Hanton white box.png",
 "destPath": '' ,
 "FileSize": 18566,
 "FileTransferTime": 0.0068,
 "time": "15/12/2021 16:13:04",
 "Encryption time": ,
},
{
 " Name ": "Save 1",
 "FileSource": "C:/Users/Hanton/Desktop/Tout/CESI/ASSOS\log.json",
 "FileTarget": "C:/Users/Hanton/Desktop/Tout/CESI/A1\log.json",
 "destPath": '' ,
 "FileSize": 875672,
 "FileTransferTime": 0.0069,
 "time": "15/12/2021 16:20:18",
 "Encryption time": ,
},
{
 " Name ": "Save 1",
 "FileSource": "C:/Users/Hanton/Desktop/Tout/CESI/ASSOS\logIRT.json",
 "FileTarget": "C:/Users/Hanton/Desktop/Tout/CESI/A1\logIRT.json",
 "destPath": '' ,
 "FileSize": 150,
 "FileTransferTime": 0.0075,
 "time": "15/12/2021 16:20:18",
 "Encryption time": ,
},
{
 " Name ": "Save 1",
 "FileSource": "C:/Users/Hanton/Desktop/Tout/CESI/ASSOS\message.txt",
 "FileTarget": "C:/Users/Hanton/Desktop/Tout/CESI/A1\message.txt",
 "destPath": '' ,
 "FileSize": 1276232,
 "FileTransferTime": 0.0075,
 "time": "15/12/2021 16:20:18",
 "Encryption time": ,
},
{
 " Name ": "Save 1",
 "FileSource": "C:/Users/Hanton/Desktop/Tout/CESI/ASSOS\Papier banque.pdf",
 "FileTarget": "C:/Users/Hanton/Desktop/Tout/CESI/A1\Papier banque.pdf",
 "destPath": '' ,
 "FileSize": 478403,
 "FileTransferTime": 0.008,
 "time": "15/12/2021 16:20:20",
 "Encryption time": ,
},
{
 " Name ": "Save 1",
 "FileSource": "C:/Users/Hanton/Desktop/Tout/CESI/ASSOS\Papier_banque_vf.pdf",
 "FileTarget": "C:/Users/Hanton/Desktop/Tout/CESI/A1\Papier_banque_vf.pdf",
 "destPath": '' ,
 "FileSize": 789728,
 "FileTransferTime": 0.0068,
 "time": "15/12/2021 16:20:20",
 "Encryption time": ,
},
{
 " Name ": "Save 1",
 "FileSource": "C:/Users/Hanton/Desktop/Tout/CESI/ASSOS\test.json",
 "FileTarget": "C:/Users/Hanton/Desktop/Tout/CESI/A1\test.json",
 "destPath": '' ,
 "FileSize": 153,
 "FileTransferTime": 0.0121,
 "time": "15/12/2021 16:20:20",
 "Encryption time": ,
},
{
 " Name ": "Save 1",
 "FileSource": "C:/Users/Hanton/Desktop/Tout/CESI/ASSOS\Cresi Racing\Texte.docx",
 "FileTarget": "C:/Users/Hanton/Desktop/Tout/CESI/A1\Cresi Racing\Texte.docx",
 "destPath": '' ,
 "FileSize": 29397,
 "FileTransferTime": 0.008,
 "time": "15/12/2021 16:20:20",
 "Encryption time": ,
},
{
 " Name ": "Save 1",
 "FileSource": "C:/Users/Hanton/Desktop/Tout/CESI/ASSOS\JDR\fiche perso Ganir TES.docx",
 "FileTarget": "C:/Users/Hanton/Desktop/Tout/CESI/A1\JDR\fiche perso Ganir TES.docx",
 "destPath": '' ,
 "FileSize": 1876866,
 "FileTransferTime": 0.007,
 "time": "15/12/2021 16:20:20",
 "Encryption time": ,
},
{
 " Name ": "Save 1",
 "FileSource": "C:/Users/Hanton/Desktop/Tout/CESI/ASSOS\Sport\message.txt",
 "FileTarget": "C:/Users/Hanton/Desktop/Tout/CESI/A1\Sport\message.txt",
 "destPath": '' ,
 "FileSize": 1276232,
 "FileTransferTime": 0.0067,
 "time": "15/12/2021 16:20:21",
 "Encryption time": ,
},
{
 " Name ": "Save 1",
 "FileSource": "C:/Users/Hanton/Desktop/Tout/CESI/ASSOS\Sport\Projet CESI SPORT.docx",
 "FileTarget": "C:/Users/Hanton/Desktop/Tout/CESI/A1\Sport\Projet CESI SPORT.docx",
 "destPath": '' ,
 "FileSize": 2293225,
 "FileTransferTime": 0.0048,
 "time": "15/12/2021 16:20:21",
 "Encryption time": ,
},
{
 " Name ": "Save 1",
 "FileSource": "C:/Users/Hanton/Desktop/Tout/CESI/ASSOS\Wild box\message.txt",
 "FileTarget": "C:/Users/Hanton/Desktop/Tout/CESI/A1\Wild box\message.txt",
 "destPath": '' ,
 "FileSize": 1276232,
 "FileTransferTime": 0.0042,
 "time": "15/12/2021 16:20:21",
 "Encryption time": ,
},
{
 " Name ": "Save 1",
 "FileSource": "C:/Users/Hanton/Desktop/Tout/CESI/ASSOS\Wild box\CROPS Saver\carotte4.png",
 "FileTarget": "C:/Users/Hanton/Desktop/Tout/CESI/A1\Wild box\CROPS Saver\carotte4.png",
 "destPath": '' ,
 "FileSize": 1618473,
 "FileTransferTime": 0.0037,
 "time": "15/12/2021 16:20:21",
 "Encryption time": ,
},
{
 " Name ": "Save 1",
 "FileSource": "C:/Users/Hanton/Desktop/Tout/CESI/ASSOS\Wild box\CROPS Saver\Projectile.png",
 "FileTarget": "C:/Users/Hanton/Desktop/Tout/CESI/A1\Wild box\CROPS Saver\Projectile.png",
 "destPath": '' ,
 "FileSize": 372,
 "FileTransferTime": 0.0041,
 "time": "15/12/2021 16:20:21",
 "Encryption time": ,
},
{
 " Name ": "Save 1",
 "FileSource": "C:/Users/Hanton/Desktop/Tout/CESI/ASSOS\Wild box\Projet solo\Stratégie tour par tour en 1v1.docx",
 "FileTarget": "C:/Users/Hanton/Desktop/Tout/CESI/A1\Wild box\Projet solo\Stratégie tour par tour en 1v1.docx",
 "destPath": '' ,
 "FileSize": 25719,
 "FileTransferTime": 0.0036,
 "time": "15/12/2021 16:20:21",
 "Encryption time": ,
},
{
 " Name ": "Save 1",
 "FileSource": "C:/Users/Hanton/Desktop/Tout/CESI/ASSOS\Wild box\Projet solo\test map.tmx",
 "FileTarget": "C:/Users/Hanton/Desktop/Tout/CESI/A1\Wild box\Projet solo\test map.tmx",
 "destPath": '' ,
 "FileSize": 20552,
 "FileTransferTime": 0.004,
 "time": "15/12/2021 16:20:21",
 "Encryption time": ,
},
{
 " Name ": "Save 1",
 "FileSource": "C:/Users/Hanton/Desktop/Tout/CESI/ASSOS\Wild box\Images\Hanton\Hanton black box.png",
 "FileTarget": "C:/Users/Hanton/Desktop/Tout/CESI/A1\Wild box\Images\Hanton\Hanton black box.png",
 "destPath": '' ,
 "FileSize": 18654,
 "FileTransferTime": 0.0036,
 "time": "15/12/2021 16:20:21",
 "Encryption time": ,
},
{
 " Name ": "Save 1",
 "FileSource": "C:/Users/Hanton/Desktop/Tout/CESI/ASSOS\Wild box\Images\Hanton\Hanton Pixel Perfect.png",
 "FileTarget": "C:/Users/Hanton/Desktop/Tout/CESI/A1\Wild box\Images\Hanton\Hanton Pixel Perfect.png",
 "destPath": '' ,
 "FileSize": 528,
 "FileTransferTime": 0.0035,
 "time": "15/12/2021 16:20:21",
 "Encryption time": ,
},
{
 " Name ": "Save 1",
 "FileSource": "C:/Users/Hanton/Desktop/Tout/CESI/ASSOS\Wild box\Images\Hanton\Hanton white box.png",
 "FileTarget": "C:/Users/Hanton/Desktop/Tout/CESI/A1\Wild box\Images\Hanton\Hanton white box.png",
 "destPath": '' ,
 "FileSize": 18566,
 "FileTransferTime": 0.0038,
 "time": "15/12/2021 16:20:21",
 "Encryption time": ,
},
{
 " Name ": "Save 1",
 "FileSource": "C:/Users/Hanton/Desktop/Tout/CESI/ASSOS\log.json",
 "FileTarget": "C:/Users/Hanton/Desktop/Tout/CESI/A1\log.json",
 "destPath": '' ,
 "FileSize": 875672,
 "FileTransferTime": 0.0161,
 "time": "15/12/2021 16:28:18",
 "Encryption time": ,
},
{
 " Name ": "Save 1",
 "FileSource": "C:/Users/Hanton/Desktop/Tout/CESI/ASSOS\logIRT.json",
 "FileTarget": "C:/Users/Hanton/Desktop/Tout/CESI/A1\logIRT.json",
 "destPath": '' ,
 "FileSize": 150,
 "FileTransferTime": 0.0092,
 "time": "15/12/2021 16:28:18",
 "Encryption time": ,
},
{
 " Name ": "Save 1",
 "FileSource": "C:/Users/Hanton/Desktop/Tout/CESI/ASSOS\message.txt",
 "FileTarget": "C:/Users/Hanton/Desktop/Tout/CESI/A1\message.txt",
 "destPath": '' ,
 "FileSize": 1276232,
 "FileTransferTime": 0.0085,
 "time": "15/12/2021 16:28:18",
 "Encryption time": ,
},
{
 " Name ": "Save 1",
 "FileSource": "C:/Users/Hanton/Desktop/Tout/CESI/ASSOS\Papier banque.pdf",
 "FileTarget": "C:/Users/Hanton/Desktop/Tout/CESI/A1\Papier banque.pdf",
 "destPath": '' ,
 "FileSize": 478403,
 "FileTransferTime": 0.0073,
 "time": "15/12/2021 16:28:19",
 "Encryption time": ,
},
{
 " Name ": "Save 1",
 "FileSource": "C:/Users/Hanton/Desktop/Tout/CESI/ASSOS\Papier_banque_vf.pdf",
 "FileTarget": "C:/Users/Hanton/Desktop/Tout/CESI/A1\Papier_banque_vf.pdf",
 "destPath": '' ,
 "FileSize": 789728,
 "FileTransferTime": 0.0074,
 "time": "15/12/2021 16:28:19",
 "Encryption time": ,
},
{
 " Name ": "Save 1",
 "FileSource": "C:/Users/Hanton/Desktop/Tout/CESI/ASSOS\test.json",
 "FileTarget": "C:/Users/Hanton/Desktop/Tout/CESI/A1\test.json",
 "destPath": '' ,
 "FileSize": 153,
 "FileTransferTime": 0.0065,
 "time": "15/12/2021 16:28:19",
 "Encryption time": ,
},
{
 " Name ": "Save 1",
 "FileSource": "C:/Users/Hanton/Desktop/Tout/CESI/ASSOS\Cresi Racing\Texte.docx",
 "FileTarget": "C:/Users/Hanton/Desktop/Tout/CESI/A1\Cresi Racing\Texte.docx",
 "destPath": '' ,
 "FileSize": 29397,
 "FileTransferTime": 0.0074,
 "time": "15/12/2021 16:28:19",
 "Encryption time": ,
},
{
 " Name ": "Save 1",
 "FileSource": "C:/Users/Hanton/Desktop/Tout/CESI/ASSOS\JDR\fiche perso Ganir TES.docx",
 "FileTarget": "C:/Users/Hanton/Desktop/Tout/CESI/A1\JDR\fiche perso Ganir TES.docx",
 "destPath": '' ,
 "FileSize": 1876866,
 "FileTransferTime": 0.0082,
 "time": "15/12/2021 16:28:20",
 "Encryption time": ,
},
{
 " Name ": "Save 1",
 "FileSource": "C:/Users/Hanton/Desktop/Tout/CESI/ASSOS\Sport\message.txt",
 "FileTarget": "C:/Users/Hanton/Desktop/Tout/CESI/A1\Sport\message.txt",
 "destPath": '' ,
 "FileSize": 1276232,
 "FileTransferTime": 0.0068,
 "time": "15/12/2021 16:28:20",
 "Encryption time": ,
},
{
 " Name ": "Save 1",
 "FileSource": "C:/Users/Hanton/Desktop/Tout/CESI/ASSOS\Sport\Projet CESI SPORT.docx",
 "FileTarget": "C:/Users/Hanton/Desktop/Tout/CESI/A1\Sport\Projet CESI SPORT.docx",
 "destPath": '' ,
 "FileSize": 2293225,
 "FileTransferTime": 0.0041,
 "time": "15/12/2021 16:28:20",
 "Encryption time": ,
},
{
 " Name ": "Save 1",
 "FileSource": "C:/Users/Hanton/Desktop/Tout/CESI/ASSOS\Wild box\message.txt",
 "FileTarget": "C:/Users/Hanton/Desktop/Tout/CESI/A1\Wild box\message.txt",
 "destPath": '' ,
 "FileSize": 1276232,
 "FileTransferTime": 0.004,
 "time": "15/12/2021 16:28:20",
 "Encryption time": ,
},
{
 " Name ": "Save 1",
 "FileSource": "C:/Users/Hanton/Desktop/Tout/CESI/ASSOS\Wild box\CROPS Saver\carotte4.png",
 "FileTarget": "C:/Users/Hanton/Desktop/Tout/CESI/A1\Wild box\CROPS Saver\carotte4.png",
 "destPath": '' ,
 "FileSize": 1618473,
 "FileTransferTime": 0.0057,
 "time": "15/12/2021 16:28:20",
 "Encryption time": ,
},
{
 " Name ": "Save 1",
 "FileSource": "C:/Users/Hanton/Desktop/Tout/CESI/ASSOS\Wild box\CROPS Saver\Projectile.png",
 "FileTarget": "C:/Users/Hanton/Desktop/Tout/CESI/A1\Wild box\CROPS Saver\Projectile.png",
 "destPath": '' ,
 "FileSize": 372,
 "FileTransferTime": 0.0058,
 "time": "15/12/2021 16:28:20",
 "Encryption time": ,
},
{
 " Name ": "Save 1",
 "FileSource": "C:/Users/Hanton/Desktop/Tout/CESI/ASSOS\log.json",
 "FileTarget": "C:/Users/Hanton/Desktop/Tout/CESI/A1\log.json",
 "destPath": '' ,
 "FileSize": 875672,
 "FileTransferTime": 0.0062,
 "time": "15/12/2021 16:29:28",
 "Encryption time": ,
},
{
 " Name ": "Save 1",
 "FileSource": "C:/Users/Hanton/Desktop/Tout/CESI/ASSOS\logIRT.json",
 "FileTarget": "C:/Users/Hanton/Desktop/Tout/CESI/A1\logIRT.json",
 "destPath": '' ,
 "FileSize": 150,
 "FileTransferTime": 0.0044,
 "time": "15/12/2021 16:29:28",
 "Encryption time": ,
},
{
 " Name ": "Save 1",
 "FileSource": "C:/Users/Hanton/Desktop/Tout/CESI/ASSOS\message.txt",
 "FileTarget": "C:/Users/Hanton/Desktop/Tout/CESI/A1\message.txt",
 "destPath": '' ,
 "FileSize": 1276232,
 "FileTransferTime": 0.0037,
 "time": "15/12/2021 16:29:28",
 "Encryption time": ,
},
{
 " Name ": "Save 1",
 "FileSource": "C:/Users/Hanton/Desktop/Tout/CESI/ASSOS\Papier banque.pdf",
 "FileTarget": "C:/Users/Hanton/Desktop/Tout/CESI/A1\Papier banque.pdf",
 "destPath": '' ,
 "FileSize": 478403,
 "FileTransferTime": 0.0042,
 "time": "15/12/2021 16:29:30",
 "Encryption time": ,
},
{
 " Name ": "Save 1",
 "FileSource": "C:/Users/Hanton/Desktop/Tout/CESI/ASSOS\Papier_banque_vf.pdf",
 "FileTarget": "C:/Users/Hanton/Desktop/Tout/CESI/A1\Papier_banque_vf.pdf",
 "destPath": '' ,
 "FileSize": 789728,
 "FileTransferTime": 0.0041,
 "time": "15/12/2021 16:29:30",
 "Encryption time": ,
},
{
 " Name ": "Save 1",
 "FileSource": "C:/Users/Hanton/Desktop/Tout/CESI/ASSOS\test.json",
 "FileTarget": "C:/Users/Hanton/Desktop/Tout/CESI/A1\test.json",
 "destPath": '' ,
 "FileSize": 153,
 "FileTransferTime": 0.0038,
 "time": "15/12/2021 16:29:30",
 "Encryption time": ,
},
{
 " Name ": "Save 1",
 "FileSource": "C:/Users/Hanton/Desktop/Tout/CESI/ASSOS\Cresi Racing\Texte.docx",
 "FileTarget": "C:/Users/Hanton/Desktop/Tout/CESI/A1\Cresi Racing\Texte.docx",
 "destPath": '' ,
 "FileSize": 29397,
 "FileTransferTime": 0.004,
 "time": "15/12/2021 16:29:30",
 "Encryption time": ,
},
{
 " Name ": "Save 1",
 "FileSource": "C:/Users/Hanton/Desktop/Tout/CESI/ASSOS\JDR\fiche perso Ganir TES.docx",
 "FileTarget": "C:/Users/Hanton/Desktop/Tout/CESI/A1\JDR\fiche perso Ganir TES.docx",
 "destPath": '' ,
 "FileSize": 1876866,
 "FileTransferTime": 0.0037,
 "time": "15/12/2021 16:29:30",
 "Encryption time": ,
},
{
 " Name ": "Save 1",
 "FileSource": "C:/Users/Hanton/Desktop/Tout/CESI/ASSOS\Sport\message.txt",
 "FileTarget": "C:/Users/Hanton/Desktop/Tout/CESI/A1\Sport\message.txt",
 "destPath": '' ,
 "FileSize": 1276232,
 "FileTransferTime": 0.004,
 "time": "15/12/2021 16:29:30",
 "Encryption time": ,
},
{
 " Name ": "Save 1",
 "FileSource": "C:/Users/Hanton/Desktop/Tout/CESI/ASSOS\Sport\Projet CESI SPORT.docx",
 "FileTarget": "C:/Users/Hanton/Desktop/Tout/CESI/A1\Sport\Projet CESI SPORT.docx",
 "destPath": '' ,
 "FileSize": 2293225,
 "FileTransferTime": 0.0039,
 "time": "15/12/2021 16:29:30",
 "Encryption time": ,
},
{
 " Name ": "Save 1",
 "FileSource": "C:/Users/Hanton/Desktop/Tout/CESI/ASSOS\Wild box\message.txt",
 "FileTarget": "C:/Users/Hanton/Desktop/Tout/CESI/A1\Wild box\message.txt",
 "destPath": '' ,
 "FileSize": 1276232,
 "FileTransferTime": 0.0037,
 "time": "15/12/2021 16:29:30",
 "Encryption time": ,
},
{
 " Name ": "Save 1",
 "FileSource": "C:/Users/Hanton/Desktop/Tout/CESI/ASSOS\Wild box\CROPS Saver\carotte4.png",
 "FileTarget": "C:/Users/Hanton/Desktop/Tout/CESI/A1\Wild box\CROPS Saver\carotte4.png",
 "destPath": '' ,
 "FileSize": 1618473,
 "FileTransferTime": 0.0073,
 "time": "15/12/2021 16:29:30",
 "Encryption time": ,
},
{
 " Name ": "Save 1",
 "FileSource": "C:/Users/Hanton/Desktop/Tout/CESI/ASSOS\Wild box\CROPS Saver\Projectile.png",
 "FileTarget": "C:/Users/Hanton/Desktop/Tout/CESI/A1\Wild box\CROPS Saver\Projectile.png",
 "destPath": '' ,
 "FileSize": 372,
 "FileTransferTime": 0.0067,
 "time": "15/12/2021 16:29:31",
 "Encryption time": ,
},
{
 " Name ": "Save 1",
 "FileSource": "C:/Users/Hanton/Desktop/Tout/CESI/ASSOS\Wild box\Projet solo\Stratégie tour par tour en 1v1.docx",
 "FileTarget": "C:/Users/Hanton/Desktop/Tout/CESI/A1\Wild box\Projet solo\Stratégie tour par tour en 1v1.docx",
 "destPath": '' ,
 "FileSize": 25719,
 "FileTransferTime": 0.004,
 "time": "15/12/2021 16:29:31",
 "Encryption time": ,
},
{
 " Name ": "Save 1",
 "FileSource": "C:/Users/Hanton/Desktop/Tout/CESI/ASSOS\Wild box\Projet solo\test map.tmx",
 "FileTarget": "C:/Users/Hanton/Desktop/Tout/CESI/A1\Wild box\Projet solo\test map.tmx",
 "destPath": '' ,
 "FileSize": 20552,
 "FileTransferTime": 0.0038,
 "time": "15/12/2021 16:29:31",
 "Encryption time": ,
},
{
 " Name ": "Save 1",
 "FileSource": "C:/Users/Hanton/Desktop/Tout/CESI/ASSOS\Wild box\Images\Hanton\Hanton black box.png",
 "FileTarget": "C:/Users/Hanton/Desktop/Tout/CESI/A1\Wild box\Images\Hanton\Hanton black box.png",
 "destPath": '' ,
 "FileSize": 18654,
 "FileTransferTime": 0.0039,
 "time": "15/12/2021 16:29:31",
 "Encryption time": ,
},
{
 " Name ": "Save 1",
 "FileSource": "C:/Users/Hanton/Desktop/Tout/CESI/ASSOS\Wild box\Images\Hanton\Hanton Pixel Perfect.png",
 "FileTarget": "C:/Users/Hanton/Desktop/Tout/CESI/A1\Wild box\Images\Hanton\Hanton Pixel Perfect.png",
 "destPath": '' ,
 "FileSize": 528,
 "FileTransferTime": 0.0038,
 "time": "15/12/2021 16:29:31",
 "Encryption time": ,
},
{
 " Name ": "Save 1",
 "FileSource": "C:/Users/Hanton/Desktop/Tout/CESI/ASSOS\Wild box\Images\Hanton\Hanton white box.png",
 "FileTarget": "C:/Users/Hanton/Desktop/Tout/CESI/A1\Wild box\Images\Hanton\Hanton white box.png",
 "destPath": '' ,
 "FileSize": 18566,
 "FileTransferTime": 0.0038,
 "time": "15/12/2021 16:29:31",
 "Encryption time": ,
},
{
 " Name ": "Save 1",
 "FileSource": "C:/Users/Hanton/Desktop/Tout/CESI/ASSOS\log.json",
 "FileTarget": "C:/Users/Hanton/Desktop/Tout/CESI/A1\log.json",
 "destPath": '' ,
 "FileSize": 875672,
 "FileTransferTime": 0.0303,
 "time": "15/12/2021 16:36:34",
 "Encryption time": ,
},
{
 " Name ": "Save 1",
 "FileSource": "C:/Users/Hanton/Desktop/Tout/CESI/ASSOS\logIRT.json",
 "FileTarget": "C:/Users/Hanton/Desktop/Tout/CESI/A1\logIRT.json",
 "destPath": '' ,
 "FileSize": 150,
 "FileTransferTime": 0.0061,
 "time": "15/12/2021 16:36:34",
 "Encryption time": ,
},
{
 " Name ": "Save 1",
 "FileSource": "C:/Users/Hanton/Desktop/Tout/CESI/ASSOS\message.txt",
 "FileTarget": "C:/Users/Hanton/Desktop/Tout/CESI/A1\message.txt",
 "destPath": '' ,
 "FileSize": 1276232,
 "FileTransferTime": 0.0058,
 "time": "15/12/2021 16:36:34",
 "Encryption time": ,
},
{
 " Name ": "Save 1",
 "FileSource": "C:/Users/Hanton/Desktop/Tout/CESI/ASSOS\Papier banque.pdf",
 "FileTarget": "C:/Users/Hanton/Desktop/Tout/CESI/A1\Papier banque.pdf",
 "destPath": '' ,
 "FileSize": 478403,
 "FileTransferTime": 0.0072,
 "time": "15/12/2021 16:36:36",
 "Encryption time": ,
},
{
 " Name ": "Save 1",
 "FileSource": "C:/Users/Hanton/Desktop/Tout/CESI/ASSOS\Papier_banque_vf.pdf",
 "FileTarget": "C:/Users/Hanton/Desktop/Tout/CESI/A1\Papier_banque_vf.pdf",
 "destPath": '' ,
 "FileSize": 789728,
 "FileTransferTime": 0.0121,
 "time": "15/12/2021 16:36:36",
 "Encryption time": ,
},
{
 " Name ": "Save 1",
 "FileSource": "C:/Users/Hanton/Desktop/Tout/CESI/ASSOS\test.json",
 "FileTarget": "C:/Users/Hanton/Desktop/Tout/CESI/A1\test.json",
 "destPath": '' ,
 "FileSize": 153,
 "FileTransferTime": 0.02,
 "time": "15/12/2021 16:36:36",
 "Encryption time": ,
},
{
 " Name ": "Save 1",
 "FileSource": "C:/Users/Hanton/Desktop/Tout/CESI/ASSOS\Cresi Racing\Texte.docx",
 "FileTarget": "C:/Users/Hanton/Desktop/Tout/CESI/A1\Cresi Racing\Texte.docx",
 "destPath": '' ,
 "FileSize": 29397,
 "FileTransferTime": 0.0068,
 "time": "15/12/2021 16:36:36",
 "Encryption time": ,
},
{
 " Name ": "Save 1",
 "FileSource": "C:/Users/Hanton/Desktop/Tout/CESI/ASSOS\JDR\fiche perso Ganir TES.docx",
 "FileTarget": "C:/Users/Hanton/Desktop/Tout/CESI/A1\JDR\fiche perso Ganir TES.docx",
 "destPath": '' ,
 "FileSize": 1876866,
 "FileTransferTime": 0.0076,
 "time": "15/12/2021 16:36:36",
 "Encryption time": ,
},
{
 " Name ": "Save 1",
 "FileSource": "C:/Users/Hanton/Desktop/Tout/CESI/ASSOS\Sport\message.txt",
 "FileTarget": "C:/Users/Hanton/Desktop/Tout/CESI/A1\Sport\message.txt",
 "destPath": '' ,
 "FileSize": 1276232,
 "FileTransferTime": 0.0068,
 "time": "15/12/2021 16:36:36",
 "Encryption time": ,
},
{
 " Name ": "Save 1",
 "FileSource": "C:/Users/Hanton/Desktop/Tout/CESI/ASSOS\Sport\Projet CESI SPORT.docx",
 "FileTarget": "C:/Users/Hanton/Desktop/Tout/CESI/A1\Sport\Projet CESI SPORT.docx",
 "destPath": '' ,
 "FileSize": 2293225,
 "FileTransferTime": 0.0066,
 "time": "15/12/2021 16:36:36",
 "Encryption time": ,
},
{
 " Name ": "Save 1",
 "FileSource": "C:/Users/Hanton/Desktop/Tout/CESI/ASSOS\Wild box\message.txt",
 "FileTarget": "C:/Users/Hanton/Desktop/Tout/CESI/A1\Wild box\message.txt",
 "destPath": '' ,
 "FileSize": 1276232,
 "FileTransferTime": 0.0064,
 "time": "15/12/2021 16:36:36",
 "Encryption time": ,
},
{
 " Name ": "Save 1",
 "FileSource": "C:/Users/Hanton/Desktop/Tout/CESI/ASSOS\Wild box\CROPS Saver\carotte4.png",
 "FileTarget": "C:/Users/Hanton/Desktop/Tout/CESI/A1\Wild box\CROPS Saver\carotte4.png",
 "destPath": '' ,
 "FileSize": 1618473,
 "FileTransferTime": 0.0069,
 "time": "15/12/2021 16:36:36",
 "Encryption time": ,
},
{
 " Name ": "Save 1",
 "FileSource": "C:/Users/Hanton/Desktop/Tout/CESI/ASSOS\Wild box\CROPS Saver\Projectile.png",
 "FileTarget": "C:/Users/Hanton/Desktop/Tout/CESI/A1\Wild box\CROPS Saver\Projectile.png",
 "destPath": '' ,
 "FileSize": 372,
 "FileTransferTime": 0.0052,
 "time": "15/12/2021 16:36:36",
 "Encryption time": ,
},
{
 " Name ": "Save 1",
 "FileSource": "C:/Users/Hanton/Desktop/Tout/CESI/ASSOS\Wild box\Projet solo\Stratégie tour par tour en 1v1.docx",
 "FileTarget": "C:/Users/Hanton/Desktop/Tout/CESI/A1\Wild box\Projet solo\Stratégie tour par tour en 1v1.docx",
 "destPath": '' ,
 "FileSize": 25719,
 "FileTransferTime": 0.0044,
 "time": "15/12/2021 16:36:36",
 "Encryption time": ,
},
{
 " Name ": "Save 1",
 "FileSource": "C:/Users/Hanton/Desktop/Tout/CESI/ASSOS\Wild box\Projet solo\test map.tmx",
 "FileTarget": "C:/Users/Hanton/Desktop/Tout/CESI/A1\Wild box\Projet solo\test map.tmx",
 "destPath": '' ,
 "FileSize": 20552,
 "FileTransferTime": 0.004,
 "time": "15/12/2021 16:36:36",
 "Encryption time": ,
},
{
 " Name ": "Save 1",
 "FileSource": "C:/Users/Hanton/Desktop/Tout/CESI/ASSOS\Wild box\Images\Hanton\Hanton black box.png",
 "FileTarget": "C:/Users/Hanton/Desktop/Tout/CESI/A1\Wild box\Images\Hanton\Hanton black box.png",
 "destPath": '' ,
 "FileSize": 18654,
 "FileTransferTime": 0.0039,
 "time": "15/12/2021 16:36:36",
 "Encryption time": ,
},
{
 " Name ": "Save 1",
 "FileSource": "C:/Users/Hanton/Desktop/Tout/CESI/ASSOS\Wild box\Images\Hanton\Hanton Pixel Perfect.png",
 "FileTarget": "C:/Users/Hanton/Desktop/Tout/CESI/A1\Wild box\Images\Hanton\Hanton Pixel Perfect.png",
 "destPath": '' ,
 "FileSize": 528,
 "FileTransferTime": 0.0045,
 "time": "15/12/2021 16:36:36",
 "Encryption time": ,
},
{
 " Name ": "Save 1",
 "FileSource": "C:/Users/Hanton/Desktop/Tout/CESI/ASSOS\Wild box\Images\Hanton\Hanton white box.png",
 "FileTarget": "C:/Users/Hanton/Desktop/Tout/CESI/A1\Wild box\Images\Hanton\Hanton white box.png",
 "destPath": '' ,
 "FileSize": 18566,
 "FileTransferTime": 0.0039,
 "time": "15/12/2021 16:36:36",
 "Encryption time": ,
},
{
 " Name ": "Save 1",
 "FileSource": "C:/Users/Hanton/Desktop/Tout/CESI/ASSOS\log.json",
 "FileTarget": "C:/Users/Hanton/Desktop/Tout/CESI/A1\log.json",
 "destPath": '' ,
 "FileSize": 875672,
 "FileTransferTime": 0.007,
 "time": "15/12/2021 16:37:36",
 "Encryption time": ,
},
{
 " Name ": "Save 1",
 "FileSource": "C:/Users/Hanton/Desktop/Tout/CESI/ASSOS\logIRT.json",
 "FileTarget": "C:/Users/Hanton/Desktop/Tout/CESI/A1\logIRT.json",
 "destPath": '' ,
 "FileSize": 150,
 "FileTransferTime": 0.0079,
 "time": "15/12/2021 16:37:36",
 "Encryption time": ,
},
{
 " Name ": "Save 1",
 "FileSource": "C:/Users/Hanton/Desktop/Tout/CESI/ASSOS\message.txt",
 "FileTarget": "C:/Users/Hanton/Desktop/Tout/CESI/A1\message.txt",
 "destPath": '' ,
 "FileSize": 1276232,
 "FileTransferTime": 0.0081,
 "time": "15/12/2021 16:37:36",
 "Encryption time": ,
},
{
 " Name ": "Save 1",
 "FileSource": "C:/Users/Hanton/Desktop/Tout/CESI/ASSOS\Papier banque.pdf",
 "FileTarget": "C:/Users/Hanton/Desktop/Tout/CESI/A1\Papier banque.pdf",
 "destPath": '' ,
 "FileSize": 478403,
 "FileTransferTime": 0.0088,
 "time": "15/12/2021 16:37:37",
 "Encryption time": ,
},
{
 " Name ": "Save 1",
 "FileSource": "C:/Users/Hanton/Desktop/Tout/CESI/ASSOS\Papier_banque_vf.pdf",
 "FileTarget": "C:/Users/Hanton/Desktop/Tout/CESI/A1\Papier_banque_vf.pdf",
 "destPath": '' ,
 "FileSize": 789728,
 "FileTransferTime": 0.0066,
 "time": "15/12/2021 16:37:37",
 "Encryption time": ,
},
{
 " Name ": "Save 1",
 "FileSource": "C:/Users/Hanton/Desktop/Tout/CESI/ASSOS\test.json",
 "FileTarget": "C:/Users/Hanton/Desktop/Tout/CESI/A1\test.json",
 "destPath": '' ,
 "FileSize": 153,
 "FileTransferTime": 0.0068,
 "time": "15/12/2021 16:37:37",
 "Encryption time": ,
},
{
 " Name ": "Save 1",
 "FileSource": "C:/Users/Hanton/Desktop/Tout/CESI/ASSOS\Cresi Racing\Texte.docx",
 "FileTarget": "C:/Users/Hanton/Desktop/Tout/CESI/A1\Cresi Racing\Texte.docx",
 "destPath": '' ,
 "FileSize": 29397,
 "FileTransferTime": 0.0064,
 "time": "15/12/2021 16:37:37",
 "Encryption time": ,
},
{
 " Name ": "Save 1",
 "FileSource": "C:/Users/Hanton/Desktop/Tout/CESI/ASSOS\JDR\fiche perso Ganir TES.docx",
 "FileTarget": "C:/Users/Hanton/Desktop/Tout/CESI/A1\JDR\fiche perso Ganir TES.docx",
 "destPath": '' ,
 "FileSize": 1876866,
 "FileTransferTime": 0.0077,
 "time": "15/12/2021 16:37:37",
 "Encryption time": ,
},
{
 " Name ": "Save 1",
 "FileSource": "C:/Users/Hanton/Desktop/Tout/CESI/ASSOS\Sport\message.txt",
 "FileTarget": "C:/Users/Hanton/Desktop/Tout/CESI/A1\Sport\message.txt",
 "destPath": '' ,
 "FileSize": 1276232,
 "FileTransferTime": 0.0076,
 "time": "15/12/2021 16:37:37",
 "Encryption time": ,
},
{
 " Name ": "Save 1",
 "FileSource": "C:/Users/Hanton/Desktop/Tout/CESI/ASSOS\Sport\Projet CESI SPORT.docx",
 "FileTarget": "C:/Users/Hanton/Desktop/Tout/CESI/A1\Sport\Projet CESI SPORT.docx",
 "destPath": '' ,
 "FileSize": 2293225,
 "FileTransferTime": 0.0055,
 "time": "15/12/2021 16:37:38",
 "Encryption time": ,
},
{
 " Name ": "Save 1",
 "FileSource": "C:/Users/Hanton/Desktop/Tout/CESI/ASSOS\Wild box\message.txt",
 "FileTarget": "C:/Users/Hanton/Desktop/Tout/CESI/A1\Wild box\message.txt",
 "destPath": '' ,
 "FileSize": 1276232,
 "FileTransferTime": 0.0051,
 "time": "15/12/2021 16:37:38",
 "Encryption time": ,
},
{
 " Name ": "Save 1",
 "FileSource": "C:/Users/Hanton/Desktop/Tout/CESI/ASSOS\Wild box\CROPS Saver\carotte4.png",
 "FileTarget": "C:/Users/Hanton/Desktop/Tout/CESI/A1\Wild box\CROPS Saver\carotte4.png",
 "destPath": '' ,
 "FileSize": 1618473,
 "FileTransferTime": 0.0044,
 "time": "15/12/2021 16:37:38",
 "Encryption time": ,
},
{
 " Name ": "Save 1",
 "FileSource": "C:/Users/Hanton/Desktop/Tout/CESI/ASSOS\Wild box\CROPS Saver\Projectile.png",
 "FileTarget": "C:/Users/Hanton/Desktop/Tout/CESI/A1\Wild box\CROPS Saver\Projectile.png",
 "destPath": '' ,
 "FileSize": 372,
 "FileTransferTime": 0.0057,
 "time": "15/12/2021 16:37:38",
 "Encryption time": ,
},
{
 " Name ": "Save 1",
 "FileSource": "C:/Users/Hanton/Desktop/Tout/CESI/ASSOS\log.json",
 "FileTarget": "C:/Users/Hanton/Desktop/Tout/CESI/A1\log.json",
 "destPath": '' ,
 "FileSize": 875672,
 "FileTransferTime": 0.0043,
 "time": "15/12/2021 16:38:16",
 "Encryption time": ,
},
{
 " Name ": "Save 1",
 "FileSource": "C:/Users/Hanton/Desktop/Tout/CESI/ASSOS\logIRT.json",
 "FileTarget": "C:/Users/Hanton/Desktop/Tout/CESI/A1\logIRT.json",
 "destPath": '' ,
 "FileSize": 150,
 "FileTransferTime": 0.0038,
 "time": "15/12/2021 16:38:16",
 "Encryption time": ,
},
{
 " Name ": "Save 1",
 "FileSource": "C:/Users/Hanton/Desktop/Tout/CESI/ASSOS\message.txt",
 "FileTarget": "C:/Users/Hanton/Desktop/Tout/CESI/A1\message.txt",
 "destPath": '' ,
 "FileSize": 1276232,
 "FileTransferTime": 0.0038,
 "time": "15/12/2021 16:38:16",
 "Encryption time": ,
},
{
 " Name ": "Save 1",
 "FileSource": "C:/Users/Hanton/Desktop/Tout/CESI/ASSOS\Papier banque.pdf",
 "FileTarget": "C:/Users/Hanton/Desktop/Tout/CESI/A1\Papier banque.pdf",
 "destPath": '' ,
 "FileSize": 478403,
 "FileTransferTime": 0.0045,
 "time": "15/12/2021 16:38:17",
 "Encryption time": ,
},
{
 " Name ": "Save 1",
 "FileSource": "C:/Users/Hanton/Desktop/Tout/CESI/ASSOS\Papier_banque_vf.pdf",
 "FileTarget": "C:/Users/Hanton/Desktop/Tout/CESI/A1\Papier_banque_vf.pdf",
 "destPath": '' ,
 "FileSize": 789728,
 "FileTransferTime": 0.0047,
 "time": "15/12/2021 16:38:17",
 "Encryption time": ,
},
{
 " Name ": "Save 1",
 "FileSource": "C:/Users/Hanton/Desktop/Tout/CESI/ASSOS\test.json",
 "FileTarget": "C:/Users/Hanton/Desktop/Tout/CESI/A1\test.json",
 "destPath": '' ,
 "FileSize": 153,
 "FileTransferTime": 0.0052,
 "time": "15/12/2021 16:38:17",
 "Encryption time": ,
},
{
 " Name ": "Save 1",
 "FileSource": "C:/Users/Hanton/Desktop/Tout/CESI/ASSOS\Cresi Racing\Texte.docx",
 "FileTarget": "C:/Users/Hanton/Desktop/Tout/CESI/A1\Cresi Racing\Texte.docx",
 "destPath": '' ,
 "FileSize": 29397,
 "FileTransferTime": 0.0051,
 "time": "15/12/2021 16:38:17",
 "Encryption time": ,
},
{
 " Name ": "Save 1",
 "FileSource": "C:/Users/Hanton/Desktop/Tout/CESI/ASSOS\JDR\fiche perso Ganir TES.docx",
 "FileTarget": "C:/Users/Hanton/Desktop/Tout/CESI/A1\JDR\fiche perso Ganir TES.docx",
 "destPath": '' ,
 "FileSize": 1876866,
 "FileTransferTime": 0.0047,
 "time": "15/12/2021 16:38:17",
 "Encryption time": ,
},
{
 " Name ": "Save 1",
 "FileSource": "C:/Users/Hanton/Desktop/Tout/CESI/ASSOS\Sport\message.txt",
 "FileTarget": "C:/Users/Hanton/Desktop/Tout/CESI/A1\Sport\message.txt",
 "destPath": '' ,
 "FileSize": 1276232,
 "FileTransferTime": 0.0047,
 "time": "15/12/2021 16:38:17",
 "Encryption time": ,
},
{
 " Name ": "Save 1",
 "FileSource": "C:/Users/Hanton/Desktop/Tout/CESI/ASSOS\Sport\Projet CESI SPORT.docx",
 "FileTarget": "C:/Users/Hanton/Desktop/Tout/CESI/A1\Sport\Projet CESI SPORT.docx",
 "destPath": '' ,
 "FileSize": 2293225,
 "FileTransferTime": 0.0046,
 "time": "15/12/2021 16:38:17",
 "Encryption time": ,
},
{
 " Name ": "Save 1",
 "FileSource": "C:/Users/Hanton/Desktop/Tout/CESI/ASSOS\Wild box\message.txt",
 "FileTarget": "C:/Users/Hanton/Desktop/Tout/CESI/A1\Wild box\message.txt",
 "destPath": '' ,
 "FileSize": 1276232,
 "FileTransferTime": 0.0057,
 "time": "15/12/2021 16:38:17",
 "Encryption time": ,
},
{
 " Name ": "Save 1",
 "FileSource": "C:/Users/Hanton/Desktop/Tout/CESI/ASSOS\Wild box\CROPS Saver\carotte4.png",
 "FileTarget": "C:/Users/Hanton/Desktop/Tout/CESI/A1\Wild box\CROPS Saver\carotte4.png",
 "destPath": '' ,
 "FileSize": 1618473,
 "FileTransferTime": 0.0055,
 "time": "15/12/2021 16:38:18",
 "Encryption time": ,
},
{
 " Name ": "Save 1",
 "FileSource": "C:/Users/Hanton/Desktop/Tout/CESI/ASSOS\Wild box\CROPS Saver\Projectile.png",
 "FileTarget": "C:/Users/Hanton/Desktop/Tout/CESI/A1\Wild box\CROPS Saver\Projectile.png",
 "destPath": '' ,
 "FileSize": 372,
 "FileTransferTime": 0.0045,
 "time": "15/12/2021 16:38:18",
 "Encryption time": ,
},
{
 " Name ": "Save 1",
 "FileSource": "C:/Users/Hanton/Desktop/Tout/CESI/ASSOS\Wild box\Projet solo\Stratégie tour par tour en 1v1.docx",
 "FileTarget": "C:/Users/Hanton/Desktop/Tout/CESI/A1\Wild box\Projet solo\Stratégie tour par tour en 1v1.docx",
 "destPath": '' ,
 "FileSize": 25719,
 "FileTransferTime": 0.0051,
 "time": "15/12/2021 16:38:18",
 "Encryption time": ,
},
{
 " Name ": "Save 1",
 "FileSource": "C:/Users/Hanton/Desktop/Tout/CESI/ASSOS\Wild box\Projet solo\test map.tmx",
 "FileTarget": "C:/Users/Hanton/Desktop/Tout/CESI/A1\Wild box\Projet solo\test map.tmx",
 "destPath": '' ,
 "FileSize": 20552,
 "FileTransferTime": 0.004,
 "time": "15/12/2021 16:38:18",
 "Encryption time": ,
},
{
 " Name ": "Save 1",
 "FileSource": "C:/Users/Hanton/Desktop/Tout/CESI/ASSOS\Wild box\Images\Hanton\Hanton black box.png",
 "FileTarget": "C:/Users/Hanton/Desktop/Tout/CESI/A1\Wild box\Images\Hanton\Hanton black box.png",
 "destPath": '' ,
 "FileSize": 18654,
 "FileTransferTime": 0.0037,
 "time": "15/12/2021 16:38:18",
 "Encryption time": ,
},
{
 " Name ": "Save 1",
 "FileSource": "C:/Users/Hanton/Desktop/Tout/CESI/ASSOS\Wild box\Images\Hanton\Hanton Pixel Perfect.png",
 "FileTarget": "C:/Users/Hanton/Desktop/Tout/CESI/A1\Wild box\Images\Hanton\Hanton Pixel Perfect.png",
 "destPath": '' ,
 "FileSize": 528,
 "FileTransferTime": 0.0043,
 "time": "15/12/2021 16:38:18",
 "Encryption time": ,
},
{
 " Name ": "Save 1",
 "FileSource": "C:/Users/Hanton/Desktop/Tout/CESI/ASSOS\Wild box\Images\Hanton\Hanton white box.png",
 "FileTarget": "C:/Users/Hanton/Desktop/Tout/CESI/A1\Wild box\Images\Hanton\Hanton white box.png",
 "destPath": '' ,
 "FileSize": 18566,
 "FileTransferTime": 0.0045,
 "time": "15/12/2021 16:38:18",
 "Encryption time": ,
},
{
 " Name ": "Save 1",
 "FileSource": "C:/Users/Hanton/Desktop/Tout/CESI/ASSOS\log.json",
 "FileTarget": "C:/Users/Hanton/Desktop/Tout/CESI/A1\log.json",
 "destPath": '' ,
 "FileSize": 875672,
 "FileTransferTime": 0.0044,
 "time": "15/12/2021 16:38:37",
 "Encryption time": ,
},
{
 " Name ": "Save 1",
 "FileSource": "C:/Users/Hanton/Desktop/Tout/CESI/ASSOS\logIRT.json",
 "FileTarget": "C:/Users/Hanton/Desktop/Tout/CESI/A1\logIRT.json",
 "destPath": '' ,
 "FileSize": 150,
 "FileTransferTime": 0.0039,
 "time": "15/12/2021 16:38:37",
 "Encryption time": ,
},
{
 " Name ": "Save 1",
 "FileSource": "C:/Users/Hanton/Desktop/Tout/CESI/ASSOS\message.txt",
 "FileTarget": "C:/Users/Hanton/Desktop/Tout/CESI/A1\message.txt",
 "destPath": '' ,
 "FileSize": 1276232,
 "FileTransferTime": 0.0049,
 "time": "15/12/2021 16:38:37",
 "Encryption time": ,
},
{
 " Name ": "Save 1",
 "FileSource": "C:/Users/Hanton/Desktop/Tout/CESI/ASSOS\Papier banque.pdf",
 "FileTarget": "C:/Users/Hanton/Desktop/Tout/CESI/A1\Papier banque.pdf",
 "destPath": '' ,
 "FileSize": 478403,
 "FileTransferTime": 0.0043,
 "time": "15/12/2021 16:38:39",
 "Encryption time": ,
},
{
 " Name ": "Save 1",
 "FileSource": "C:/Users/Hanton/Desktop/Tout/CESI/ASSOS\Papier_banque_vf.pdf",
 "FileTarget": "C:/Users/Hanton/Desktop/Tout/CESI/A1\Papier_banque_vf.pdf",
 "destPath": '' ,
 "FileSize": 789728,
 "FileTransferTime": 0.0047,
 "time": "15/12/2021 16:38:39",
 "Encryption time": ,
},
{
 " Name ": "Save 1",
 "FileSource": "C:/Users/Hanton/Desktop/Tout/CESI/ASSOS\test.json",
 "FileTarget": "C:/Users/Hanton/Desktop/Tout/CESI/A1\test.json",
 "destPath": '' ,
 "FileSize": 153,
 "FileTransferTime": 0.0045,
 "time": "15/12/2021 16:38:39",
 "Encryption time": ,
},
{
 " Name ": "Save 1",
 "FileSource": "C:/Users/Hanton/Desktop/Tout/CESI/ASSOS\Cresi Racing\Texte.docx",
 "FileTarget": "C:/Users/Hanton/Desktop/Tout/CESI/A1\Cresi Racing\Texte.docx",
 "destPath": '' ,
 "FileSize": 29397,
 "FileTransferTime": 0.0042,
 "time": "15/12/2021 16:38:39",
 "Encryption time": ,
},
{
 " Name ": "Save 1",
 "FileSource": "C:/Users/Hanton/Desktop/Tout/CESI/ASSOS\JDR\fiche perso Ganir TES.docx",
 "FileTarget": "C:/Users/Hanton/Desktop/Tout/CESI/A1\JDR\fiche perso Ganir TES.docx",
 "destPath": '' ,
 "FileSize": 1876866,
 "FileTransferTime": 0.0044,
 "time": "15/12/2021 16:38:39",
 "Encryption time": ,
},
{
 " Name ": "Save 1",
 "FileSource": "C:/Users/Hanton/Desktop/Tout/CESI/ASSOS\Sport\message.txt",
 "FileTarget": "C:/Users/Hanton/Desktop/Tout/CESI/A1\Sport\message.txt",
 "destPath": '' ,
 "FileSize": 1276232,
 "FileTransferTime": 0.0044,
 "time": "15/12/2021 16:38:39",
 "Encryption time": ,
},
{
 " Name ": "Save 1",
 "FileSource": "C:/Users/Hanton/Desktop/Tout/CESI/ASSOS\Sport\Projet CESI SPORT.docx",
 "FileTarget": "C:/Users/Hanton/Desktop/Tout/CESI/A1\Sport\Projet CESI SPORT.docx",
 "destPath": '' ,
 "FileSize": 2293225,
 "FileTransferTime": 0.0042,
 "time": "15/12/2021 16:38:39",
 "Encryption time": ,
},
{
 " Name ": "Save 1",
 "FileSource": "C:/Users/Hanton/Desktop/Tout/CESI/ASSOS\Wild box\message.txt",
 "FileTarget": "C:/Users/Hanton/Desktop/Tout/CESI/A1\Wild box\message.txt",
 "destPath": '' ,
 "FileSize": 1276232,
 "FileTransferTime": 0.0049,
 "time": "15/12/2021 16:38:39",
 "Encryption time": ,
},
{
 " Name ": "Save 1",
 "FileSource": "C:/Users/Hanton/Desktop/Tout/CESI/ASSOS\Wild box\CROPS Saver\carotte4.png",
 "FileTarget": "C:/Users/Hanton/Desktop/Tout/CESI/A1\Wild box\CROPS Saver\carotte4.png",
 "destPath": '' ,
 "FileSize": 1618473,
 "FileTransferTime": 0.0052,
 "time": "15/12/2021 16:38:39",
 "Encryption time": ,
},
{
 " Name ": "Save 1",
 "FileSource": "C:/Users/Hanton/Desktop/Tout/CESI/ASSOS\Wild box\CROPS Saver\Projectile.png",
 "FileTarget": "C:/Users/Hanton/Desktop/Tout/CESI/A1\Wild box\CROPS Saver\Projectile.png",
 "destPath": '' ,
 "FileSize": 372,
 "FileTransferTime": 0.0059,
 "time": "15/12/2021 16:38:39",
 "Encryption time": ,
},
{
 " Name ": "Save 1",
 "FileSource": "C:/Users/Hanton/Desktop/Tout/CESI/ASSOS\Wild box\Projet solo\Stratégie tour par tour en 1v1.docx",
 "FileTarget": "C:/Users/Hanton/Desktop/Tout/CESI/A1\Wild box\Projet solo\Stratégie tour par tour en 1v1.docx",
 "destPath": '' ,
 "FileSize": 25719,
 "FileTransferTime": 0.0057,
 "time": "15/12/2021 16:38:39",
 "Encryption time": ,
},
{
 " Name ": "Save 1",
 "FileSource": "C:/Users/Hanton/Desktop/Tout/CESI/ASSOS\Wild box\Projet solo\test map.tmx",
 "FileTarget": "C:/Users/Hanton/Desktop/Tout/CESI/A1\Wild box\Projet solo\test map.tmx",
 "destPath": '' ,
 "FileSize": 20552,
 "FileTransferTime": 0.0042,
 "time": "15/12/2021 16:38:39",
 "Encryption time": ,
},
{
 " Name ": "Save 1",
 "FileSource": "C:/Users/Hanton/Desktop/Tout/CESI/ASSOS\Wild box\Images\Hanton\Hanton black box.png",
 "FileTarget": "C:/Users/Hanton/Desktop/Tout/CESI/A1\Wild box\Images\Hanton\Hanton black box.png",
 "destPath": '' ,
 "FileSize": 18654,
 "FileTransferTime": 0.0043,
 "time": "15/12/2021 16:38:39",
 "Encryption time": ,
},
{
 " Name ": "Save 1",
 "FileSource": "C:/Users/Hanton/Desktop/Tout/CESI/ASSOS\Wild box\Images\Hanton\Hanton Pixel Perfect.png",
 "FileTarget": "C:/Users/Hanton/Desktop/Tout/CESI/A1\Wild box\Images\Hanton\Hanton Pixel Perfect.png",
 "destPath": '' ,
 "FileSize": 528,
 "FileTransferTime": 0.0052,
 "time": "15/12/2021 16:38:40",
 "Encryption time": ,
},
{
 " Name ": "Save 1",
 "FileSource": "C:/Users/Hanton/Desktop/Tout/CESI/ASSOS\Wild box\Images\Hanton\Hanton white box.png",
 "FileTarget": "C:/Users/Hanton/Desktop/Tout/CESI/A1\Wild box\Images\Hanton\Hanton white box.png",
 "destPath": '' ,
 "FileSize": 18566,
 "FileTransferTime": 0.0042,
 "time": "15/12/2021 16:38:40",
 "Encryption time": ,
},
{
 " Name ": "Save 1",
 "FileSource": "C:/Users/Hanton/Desktop/Tout/CESI/ASSOS\log.json",
 "FileTarget": "C:/Users/Hanton/Desktop/Tout/CESI/A1\log.json",
 "destPath": '' ,
 "FileSize": 875672,
 "FileTransferTime": 0.0068,
 "time": "15/12/2021 16:39:34",
 "Encryption time": ,
},
{
 " Name ": "Save 1",
 "FileSource": "C:/Users/Hanton/Desktop/Tout/CESI/ASSOS\logIRT.json",
 "FileTarget": "C:/Users/Hanton/Desktop/Tout/CESI/A1\logIRT.json",
 "destPath": '' ,
 "FileSize": 150,
 "FileTransferTime": 0.0079,
 "time": "15/12/2021 16:39:34",
 "Encryption time": ,
},
{
 " Name ": "Save 1",
 "FileSource": "C:/Users/Hanton/Desktop/Tout/CESI/ASSOS\message.txt",
 "FileTarget": "C:/Users/Hanton/Desktop/Tout/CESI/A1\message.txt",
 "destPath": '' ,
 "FileSize": 1276232,
 "FileTransferTime": 0.0085,
 "time": "15/12/2021 16:39:34",
 "Encryption time": ,
},
{
 " Name ": "Save 1",
 "FileSource": "C:/Users/Hanton/Desktop/Tout/CESI/ASSOS\Papier banque.pdf",
 "FileTarget": "C:/Users/Hanton/Desktop/Tout/CESI/A1\Papier banque.pdf",
 "destPath": '' ,
 "FileSize": 478403,
 "FileTransferTime": 0.0081,
 "time": "15/12/2021 16:39:35",
 "Encryption time": ,
},
{
 " Name ": "Save 1",
 "FileSource": "C:/Users/Hanton/Desktop/Tout/CESI/ASSOS\Papier_banque_vf.pdf",
 "FileTarget": "C:/Users/Hanton/Desktop/Tout/CESI/A1\Papier_banque_vf.pdf",
 "destPath": '' ,
 "FileSize": 789728,
 "FileTransferTime": 0.0067,
 "time": "15/12/2021 16:39:35",
 "Encryption time": ,
},
{
 " Name ": "Save 1",
 "FileSource": "C:/Users/Hanton/Desktop/Tout/CESI/ASSOS\test.json",
 "FileTarget": "C:/Users/Hanton/Desktop/Tout/CESI/A1\test.json",
 "destPath": '' ,
 "FileSize": 153,
 "FileTransferTime": 0.0063,
 "time": "15/12/2021 16:39:35",
 "Encryption time": ,
},
{
 " Name ": "Save 1",
 "FileSource": "C:/Users/Hanton/Desktop/Tout/CESI/ASSOS\Cresi Racing\Texte.docx",
 "FileTarget": "C:/Users/Hanton/Desktop/Tout/CESI/A1\Cresi Racing\Texte.docx",
 "destPath": '' ,
 "FileSize": 29397,
 "FileTransferTime": 0.0105,
 "time": "15/12/2021 16:39:35",
 "Encryption time": ,
},
{
 " Name ": "Save 1",
 "FileSource": "C:/Users/Hanton/Desktop/Tout/CESI/ASSOS\JDR\fiche perso Ganir TES.docx",
 "FileTarget": "C:/Users/Hanton/Desktop/Tout/CESI/A1\JDR\fiche perso Ganir TES.docx",
 "destPath": '' ,
 "FileSize": 1876866,
 "FileTransferTime": 0.0066,
 "time": "15/12/2021 16:39:35",
 "Encryption time": ,
},
{
 " Name ": "Save 1",
 "FileSource": "C:/Users/Hanton/Desktop/Tout/CESI/ASSOS\Sport\message.txt",
 "FileTarget": "C:/Users/Hanton/Desktop/Tout/CESI/A1\Sport\message.txt",
 "destPath": '' ,
 "FileSize": 1276232,
 "FileTransferTime": 0.0062,
 "time": "15/12/2021 16:39:36",
 "Encryption time": ,
},
{
 " Name ": "Save 1",
 "FileSource": "C:/Users/Hanton/Desktop/Tout/CESI/ASSOS\Sport\Projet CESI SPORT.docx",
 "FileTarget": "C:/Users/Hanton/Desktop/Tout/CESI/A1\Sport\Projet CESI SPORT.docx",
 "destPath": '' ,
 "FileSize": 2293225,
 "FileTransferTime": 0.0046,
 "time": "15/12/2021 16:39:36",
 "Encryption time": ,
},
{
 " Name ": "Save 1",
 "FileSource": "C:/Users/Hanton/Desktop/Tout/CESI/ASSOS\Wild box\message.txt",
 "FileTarget": "C:/Users/Hanton/Desktop/Tout/CESI/A1\Wild box\message.txt",
 "destPath": '' ,
 "FileSize": 1276232,
 "FileTransferTime": 0.0046,
 "time": "15/12/2021 16:39:36",
 "Encryption time": ,
},
{
 " Name ": "Save 1",
 "FileSource": "C:/Users/Hanton/Desktop/Tout/CESI/ASSOS\Wild box\CROPS Saver\carotte4.png",
 "FileTarget": "C:/Users/Hanton/Desktop/Tout/CESI/A1\Wild box\CROPS Saver\carotte4.png",
 "destPath": '' ,
 "FileSize": 1618473,
 "FileTransferTime": 0.0045,
 "time": "15/12/2021 16:39:36",
 "Encryption time": ,
},
{
 " Name ": "Save 1",
 "FileSource": "C:/Users/Hanton/Desktop/Tout/CESI/ASSOS\Wild box\CROPS Saver\Projectile.png",
 "FileTarget": "C:/Users/Hanton/Desktop/Tout/CESI/A1\Wild box\CROPS Saver\Projectile.png",
 "destPath": '' ,
 "FileSize": 372,
 "FileTransferTime": 0.005,
 "time": "15/12/2021 16:39:36",
 "Encryption time": ,
},
{
 " Name ": "Save 1",
 "FileSource": "C:/Users/Hanton/Desktop/Tout/CESI/ASSOS\Wild box\Projet solo\Stratégie tour par tour en 1v1.docx",
 "FileTarget": "C:/Users/Hanton/Desktop/Tout/CESI/A1\Wild box\Projet solo\Stratégie tour par tour en 1v1.docx",
 "destPath": '' ,
 "FileSize": 25719,
 "FileTransferTime": 0.0046,
 "time": "15/12/2021 16:39:36",
 "Encryption time": ,
},
{
 " Name ": "Save 1",
 "FileSource": "C:/Users/Hanton/Desktop/Tout/CESI/ASSOS\Wild box\Projet solo\test map.tmx",
 "FileTarget": "C:/Users/Hanton/Desktop/Tout/CESI/A1\Wild box\Projet solo\test map.tmx",
 "destPath": '' ,
 "FileSize": 20552,
 "FileTransferTime": 0.0052,
 "time": "15/12/2021 16:39:36",
 "Encryption time": ,
},
{
 " Name ": "Save 1",
 "FileSource": "C:/Users/Hanton/Desktop/Tout/CESI/ASSOS\Wild box\Images\Hanton\Hanton black box.png",
 "FileTarget": "C:/Users/Hanton/Desktop/Tout/CESI/A1\Wild box\Images\Hanton\Hanton black box.png",
 "destPath": '' ,
 "FileSize": 18654,
 "FileTransferTime": 0.0055,
 "time": "15/12/2021 16:39:36",
 "Encryption time": ,
},
{
 " Name ": "Save 1",
 "FileSource": "C:/Users/Hanton/Desktop/Tout/CESI/ASSOS\Wild box\Images\Hanton\Hanton Pixel Perfect.png",
 "FileTarget": "C:/Users/Hanton/Desktop/Tout/CESI/A1\Wild box\Images\Hanton\Hanton Pixel Perfect.png",
 "destPath": '' ,
 "FileSize": 528,
 "FileTransferTime": 0.0044,
 "time": "15/12/2021 16:39:36",
 "Encryption time": ,
},
{
 " Name ": "Save 1",
 "FileSource": "C:/Users/Hanton/Desktop/Tout/CESI/ASSOS\Wild box\Images\Hanton\Hanton white box.png",
 "FileTarget": "C:/Users/Hanton/Desktop/Tout/CESI/A1\Wild box\Images\Hanton\Hanton white box.png",
 "destPath": '' ,
 "FileSize": 18566,
 "FileTransferTime": 0.0056,
 "time": "15/12/2021 16:39:36",
 "Encryption time": ,
},
{
 " Name ": "Save 1",
 "FileSource": "C:/Users/Hanton/Desktop/Tout/CESI/ASSOS\log.json",
 "FileTarget": "C:/Users/Hanton/Desktop/Tout/CESI/A1\log.json",
 "destPath": '' ,
 "FileSize": 875672,
 "FileTransferTime": 0.0042,
 "time": "15/12/2021 16:42:15",
 "Encryption time": ,
},
{
 " Name ": "Save 1",
 "FileSource": "C:/Users/Hanton/Desktop/Tout/CESI/ASSOS\logIRT.json",
 "FileTarget": "C:/Users/Hanton/Desktop/Tout/CESI/A1\logIRT.json",
 "destPath": '' ,
 "FileSize": 150,
 "FileTransferTime": 0.0043,
 "time": "15/12/2021 16:42:15",
 "Encryption time": ,
},
{
 " Name ": "Save 1",
 "FileSource": "C:/Users/Hanton/Desktop/Tout/CESI/ASSOS\message.txt",
 "FileTarget": "C:/Users/Hanton/Desktop/Tout/CESI/A1\message.txt",
 "destPath": '' ,
 "FileSize": 1276232,
 "FileTransferTime": 0.0036,
 "time": "15/12/2021 16:42:15",
 "Encryption time": ,
},
{
 " Name ": "Save 1",
 "FileSource": "C:/Users/Hanton/Desktop/Tout/CESI/ASSOS\Papier banque.pdf",
 "FileTarget": "C:/Users/Hanton/Desktop/Tout/CESI/A1\Papier banque.pdf",
 "destPath": '' ,
 "FileSize": 478403,
 "FileTransferTime": 0.0039,
 "time": "15/12/2021 16:42:17",
 "Encryption time": ,
},
{
 " Name ": "Save 1",
 "FileSource": "C:/Users/Hanton/Desktop/Tout/CESI/ASSOS\Papier_banque_vf.pdf",
 "FileTarget": "C:/Users/Hanton/Desktop/Tout/CESI/A1\Papier_banque_vf.pdf",
 "destPath": '' ,
 "FileSize": 789728,
 "FileTransferTime": 0.0055,
 "time": "15/12/2021 16:42:17",
 "Encryption time": ,
},
{
 " Name ": "Save 1",
 "FileSource": "C:/Users/Hanton/Desktop/Tout/CESI/ASSOS\test.json",
 "FileTarget": "C:/Users/Hanton/Desktop/Tout/CESI/A1\test.json",
 "destPath": '' ,
 "FileSize": 153,
 "FileTransferTime": 0.0049,
 "time": "15/12/2021 16:42:17",
 "Encryption time": ,
},
{
 " Name ": "Save 1",
 "FileSource": "C:/Users/Hanton/Desktop/Tout/CESI/ASSOS\Cresi Racing\Texte.docx",
 "FileTarget": "C:/Users/Hanton/Desktop/Tout/CESI/A1\Cresi Racing\Texte.docx",
 "destPath": '' ,
 "FileSize": 29397,
 "FileTransferTime": 0.0041,
 "time": "15/12/2021 16:42:17",
 "Encryption time": ,
},
{
 " Name ": "Save 1",
 "FileSource": "C:/Users/Hanton/Desktop/Tout/CESI/ASSOS\JDR\fiche perso Ganir TES.docx",
 "FileTarget": "C:/Users/Hanton/Desktop/Tout/CESI/A1\JDR\fiche perso Ganir TES.docx",
 "destPath": '' ,
 "FileSize": 1876866,
 "FileTransferTime": 0.0037,
 "time": "15/12/2021 16:42:17",
 "Encryption time": ,
},
{
 " Name ": "Save 1",
 "FileSource": "C:/Users/Hanton/Desktop/Tout/CESI/ASSOS\Sport\message.txt",
 "FileTarget": "C:/Users/Hanton/Desktop/Tout/CESI/A1\Sport\message.txt",
 "destPath": '' ,
 "FileSize": 1276232,
 "FileTransferTime": 0.0046,
 "time": "15/12/2021 16:42:17",
 "Encryption time": ,
},
{
 " Name ": "Save 1",
 "FileSource": "C:/Users/Hanton/Desktop/Tout/CESI/ASSOS\Sport\Projet CESI SPORT.docx",
 "FileTarget": "C:/Users/Hanton/Desktop/Tout/CESI/A1\Sport\Projet CESI SPORT.docx",
 "destPath": '' ,
 "FileSize": 2293225,
 "FileTransferTime": 0.0048,
 "time": "15/12/2021 16:42:17",
 "Encryption time": ,
},
{
 " Name ": "Save 1",
 "FileSource": "C:/Users/Hanton/Desktop/Tout/CESI/ASSOS\Wild box\message.txt",
 "FileTarget": "C:/Users/Hanton/Desktop/Tout/CESI/A1\Wild box\message.txt",
 "destPath": '' ,
 "FileSize": 1276232,
 "FileTransferTime": 0.0052,
 "time": "15/12/2021 16:42:18",
 "Encryption time": ,
},
{
 " Name ": "Save 1",
 "FileSource": "C:/Users/Hanton/Desktop/Tout/CESI/ASSOS\Wild box\CROPS Saver\carotte4.png",
 "FileTarget": "C:/Users/Hanton/Desktop/Tout/CESI/A1\Wild box\CROPS Saver\carotte4.png",
 "destPath": '' ,
 "FileSize": 1618473,
 "FileTransferTime": 0.0049,
 "time": "15/12/2021 16:42:18",
 "Encryption time": ,
},
{
 " Name ": "Save 1",
 "FileSource": "C:/Users/Hanton/Desktop/Tout/CESI/ASSOS\Wild box\CROPS Saver\Projectile.png",
 "FileTarget": "C:/Users/Hanton/Desktop/Tout/CESI/A1\Wild box\CROPS Saver\Projectile.png",
 "destPath": '' ,
 "FileSize": 372,
 "FileTransferTime": 0.0045,
 "time": "15/12/2021 16:42:18",
 "Encryption time": ,
},
{
 " Name ": "Save 1",
 "FileSource": "C:/Users/Hanton/Desktop/Tout/CESI/ASSOS\Wild box\Projet solo\Stratégie tour par tour en 1v1.docx",
 "FileTarget": "C:/Users/Hanton/Desktop/Tout/CESI/A1\Wild box\Projet solo\Stratégie tour par tour en 1v1.docx",
 "destPath": '' ,
 "FileSize": 25719,
 "FileTransferTime": 0.005,
 "time": "15/12/2021 16:42:18",
 "Encryption time": ,
},
{
 " Name ": "Save 1",
 "FileSource": "C:/Users/Hanton/Desktop/Tout/CESI/ASSOS\log.json",
 "FileTarget": "C:/Users/Hanton/Desktop/Tout/CESI/A1\log.json",
 "destPath": '' ,
 "FileSize": 875672,
 "FileTransferTime": 0.0072,
 "time": "15/12/2021 16:44:05",
 "Encryption time": ,
},
{
 " Name ": "Save 1",
 "FileSource": "C:/Users/Hanton/Desktop/Tout/CESI/ASSOS\logIRT.json",
 "FileTarget": "C:/Users/Hanton/Desktop/Tout/CESI/A1\logIRT.json",
 "destPath": '' ,
 "FileSize": 150,
 "FileTransferTime": 0.0076,
 "time": "15/12/2021 16:44:05",
 "Encryption time": ,
},
{
 " Name ": "Save 1",
 "FileSource": "C:/Users/Hanton/Desktop/Tout/CESI/ASSOS\message.txt",
 "FileTarget": "C:/Users/Hanton/Desktop/Tout/CESI/A1\message.txt",
 "destPath": '' ,
 "FileSize": 1276232,
 "FileTransferTime": 0.0073,
 "time": "15/12/2021 16:44:05",
 "Encryption time": ,
},
{
 " Name ": "Save 1",
 "FileSource": "C:/Users/Hanton/Desktop/Tout/CESI/ASSOS\Papier banque.pdf",
 "FileTarget": "C:/Users/Hanton/Desktop/Tout/CESI/A1\Papier banque.pdf",
 "destPath": '' ,
 "FileSize": 478403,
 "FileTransferTime": 0.0069,
 "time": "15/12/2021 16:44:07",
 "Encryption time": ,
},
{
 " Name ": "Save 1",
 "FileSource": "C:/Users/Hanton/Desktop/Tout/CESI/ASSOS\Papier_banque_vf.pdf",
 "FileTarget": "C:/Users/Hanton/Desktop/Tout/CESI/A1\Papier_banque_vf.pdf",
 "destPath": '' ,
 "FileSize": 789728,
 "FileTransferTime": 0.0079,
 "time": "15/12/2021 16:44:07",
 "Encryption time": ,
},
{
 " Name ": "Save 1",
 "FileSource": "C:/Users/Hanton/Desktop/Tout/CESI/ASSOS\test.json",
 "FileTarget": "C:/Users/Hanton/Desktop/Tout/CESI/A1\test.json",
 "destPath": '' ,
 "FileSize": 153,
 "FileTransferTime": 0.006,
 "time": "15/12/2021 16:44:07",
 "Encryption time": ,
},
{
 " Name ": "Save 1",
 "FileSource": "C:/Users/Hanton/Desktop/Tout/CESI/ASSOS\Cresi Racing\Texte.docx",
 "FileTarget": "C:/Users/Hanton/Desktop/Tout/CESI/A1\Cresi Racing\Texte.docx",
 "destPath": '' ,
 "FileSize": 29397,
 "FileTransferTime": 0.0057,
 "time": "15/12/2021 16:44:07",
 "Encryption time": ,
},
{
 " Name ": "Save 1",
 "FileSource": "C:/Users/Hanton/Desktop/Tout/CESI/ASSOS\JDR\fiche perso Ganir TES.docx",
 "FileTarget": "C:/Users/Hanton/Desktop/Tout/CESI/A1\JDR\fiche perso Ganir TES.docx",
 "destPath": '' ,
 "FileSize": 1876866,
 "FileTransferTime": 0.008,
 "time": "15/12/2021 16:44:07",
 "Encryption time": ,
},
{
 " Name ": "Save 1",
 "FileSource": "C:/Users/Hanton/Desktop/Tout/CESI/ASSOS\Sport\message.txt",
 "FileTarget": "C:/Users/Hanton/Desktop/Tout/CESI/A1\Sport\message.txt",
 "destPath": '' ,
 "FileSize": 1276232,
 "FileTransferTime": 0.0061,
 "time": "15/12/2021 16:44:07",
 "Encryption time": ,
},
{
 " Name ": "Save 1",
 "FileSource": "C:/Users/Hanton/Desktop/Tout/CESI/ASSOS\Sport\Projet CESI SPORT.docx",
 "FileTarget": "C:/Users/Hanton/Desktop/Tout/CESI/A1\Sport\Projet CESI SPORT.docx",
 "destPath": '' ,
 "FileSize": 2293225,
 "FileTransferTime": 0.0049,
 "time": "15/12/2021 16:44:07",
 "Encryption time": ,
},
{
 " Name ": "Save 1",
 "FileSource": "C:/Users/Hanton/Desktop/Tout/CESI/ASSOS\Wild box\message.txt",
 "FileTarget": "C:/Users/Hanton/Desktop/Tout/CESI/A1\Wild box\message.txt",
 "destPath": '' ,
 "FileSize": 1276232,
 "FileTransferTime": 0.0045,
 "time": "15/12/2021 16:44:07",
 "Encryption time": ,
},
{
 " Name ": "Save 1",
 "FileSource": "C:/Users/Hanton/Desktop/Tout/CESI/ASSOS\Wild box\CROPS Saver\carotte4.png",
 "FileTarget": "C:/Users/Hanton/Desktop/Tout/CESI/A1\Wild box\CROPS Saver\carotte4.png",
 "destPath": '' ,
 "FileSize": 1618473,
 "FileTransferTime": 0.005,
 "time": "15/12/2021 16:44:07",
 "Encryption time": ,
},
{
 " Name ": "Save 1",
 "FileSource": "C:/Users/Hanton/Desktop/Tout/CESI/ASSOS\Wild box\CROPS Saver\Projectile.png",
 "FileTarget": "C:/Users/Hanton/Desktop/Tout/CESI/A1\Wild box\CROPS Saver\Projectile.png",
 "destPath": '' ,
 "FileSize": 372,
 "FileTransferTime": 0.0043,
 "time": "15/12/2021 16:44:07",
 "Encryption time": ,
},
{
 " Name ": "Save 1",
 "FileSource": "C:/Users/Hanton/Desktop/Tout/CESI/ASSOS\Wild box\Projet solo\Stratégie tour par tour en 1v1.docx",
 "FileTarget": "C:/Users/Hanton/Desktop/Tout/CESI/A1\Wild box\Projet solo\Stratégie tour par tour en 1v1.docx",
 "destPath": '' ,
 "FileSize": 25719,
 "FileTransferTime": 0.0044,
 "time": "15/12/2021 16:44:07",
 "Encryption time": ,
},
{
 " Name ": "Save 1",
 "FileSource": "C:/Users/Hanton/Desktop/Tout/CESI/ASSOS\Wild box\Projet solo\test map.tmx",
 "FileTarget": "C:/Users/Hanton/Desktop/Tout/CESI/A1\Wild box\Projet solo\test map.tmx",
 "destPath": '' ,
 "FileSize": 20552,
 "FileTransferTime": 0.0051,
 "time": "15/12/2021 16:44:07",
 "Encryption time": ,
},
{
 " Name ": "Save 1",
 "FileSource": "C:/Users/Hanton/Desktop/Tout/CESI/ASSOS\Wild box\Images\Hanton\Hanton black box.png",
 "FileTarget": "C:/Users/Hanton/Desktop/Tout/CESI/A1\Wild box\Images\Hanton\Hanton black box.png",
 "destPath": '' ,
 "FileSize": 18654,
 "FileTransferTime": 0.0061,
 "time": "15/12/2021 16:44:07",
 "Encryption time": ,
},
{
 " Name ": "Save 1",
 "FileSource": "C:/Users/Hanton/Desktop/Tout/CESI/ASSOS\Wild box\Images\Hanton\Hanton Pixel Perfect.png",
 "FileTarget": "C:/Users/Hanton/Desktop/Tout/CESI/A1\Wild box\Images\Hanton\Hanton Pixel Perfect.png",
 "destPath": '' ,
 "FileSize": 528,
 "FileTransferTime": 0.0047,
 "time": "15/12/2021 16:44:07",
 "Encryption time": ,
},
{
 " Name ": "Save 1",
 "FileSource": "C:/Users/Hanton/Desktop/Tout/CESI/ASSOS\Wild box\Images\Hanton\Hanton white box.png",
 "FileTarget": "C:/Users/Hanton/Desktop/Tout/CESI/A1\Wild box\Images\Hanton\Hanton white box.png",
 "destPath": '' ,
 "FileSize": 18566,
 "FileTransferTime": 0.005,
 "time": "15/12/2021 16:44:07",
 "Encryption time": ,
},